Workbook
Name Pass: '[1]Test Case_ILC'!$H$13

Sheet Version
A4: CBS-SHWE_TC_C#toStore_FO_Other
D6: Version: 1.0
A7: Version history
A8: Version | B8: Maker | C8: Revision Date | D8: Checker | E8: Approval Date | F8: Document Changes
A9: 1 | B9: VyHNT | C9: 45637 | F9: Create document

Sheet Summary
B2: Bàn giao test case
B3: Ngày | C3: 43375
B4: Giờ | C4: 15h00
B5: Tổng số case | C5: ='Scenario Test'!J21 -> 212
B7: Execute test case lần 1 theo ngày
B8: Date Status | C8: 43374 | D8: 43375 | E8: 43376 | F8: 43377 | G8: 43378 | H8: 43379 | I8: 43380
B9: Pass | C9: =COUNTIFS(TestCase!$G:$G,$B$9,TestCase!$J:$J,C8) -> 0 | D9: =COUNTIFS(TestCase!$G:$G,$B$9,TestCase!$J:$J,D8) -> 0 | E9: =COUNTIFS(TestCase!$G:$G,$B$9,TestCase!$J:$J,E8) -> 0 | F9: =COUNTIFS(TestCase!$G:$G,$B$9,TestCase!$J:$J,F8) -> 0 | G9: =COUNTIFS(TestCase!$G:$G,$B$9,TestCase!$J:$J,G8) -> 0 | H9: =COUNTIFS(TestCase!$G:$G,$B$9,TestCase!$J:$J,H8) -> 0 | I9: =COUNTIFS(TestCase!$G:$G,$B$9,TestCase!$J:$J,I8) -> 0
B10: Fail | C10: =COUNTIFS(TestCase!$G:$G,$B$10,TestCase!$J:$J,C8) -> 0 | D10: =COUNTIFS(TestCase!$G:$G,$B$10,TestCase!$J:$J,D8) -> 0 | E10: =COUNTIFS(TestCase!$G:$G,$B$10,TestCase!$J:$J,E8) -> 0 | F10: =COUNTIFS(TestCase!$G:$G,$B$10,TestCase!$J:$J,F8) -> 0 | G10: =COUNTIFS(TestCase!$G:$G,$B$10,TestCase!$J:$J,G8) -> 0 | H10: =COUNTIFS(TestCase!$G:$G,$B$10,TestCase!$J:$J,H8) -> 0 | I10: =COUNTIFS(TestCase!$G:$G,$B$10,TestCase!$J:$J,I8) -> 0
B11: Block | C11: =COUNTIFS(TestCase!$G:$G,$B$11,TestCase!$J:$J,C8) -> 0 | D11: =COUNTIFS(TestCase!$G:$G,$B$11,TestCase!$J:$J,D8) -> 0 | E11: =COUNTIFS(TestCase!$G:$G,$B$11,TestCase!$J:$J,E8) -> 0 | F11: =COUNTIFS(TestCase!$G:$G,$B$11,TestCase!$J:$J,F8) -> 0 | G11: =COUNTIFS(TestCase!$G:$G,$B$11,TestCase!$J:$J,G8) -> 0 | H11: =COUNTIFS(TestCase!$G:$G,$B$11,TestCase!$J:$J,H8) -> 0 | I11: =COUNTIFS(TestCase!$G:$G,$B$11,TestCase!$J:$J,I8) -> 0
B12: Pending | C12: =COUNTIFS(TestCase!$G:$G,$B$12,TestCase!$K:$K,C8) -> 0 | D12: =COUNTIFS(TestCase!$G:$G,$B$12,TestCase!$K:$K,D8) -> 0 | E12: =COUNTIFS(TestCase!$G:$G,$B$12,TestCase!$K:$K,E8) -> 0 | F12: =COUNTIFS(TestCase!$G:$G,$B$12,TestCase!$K:$K,F8) -> 0 | G12: =COUNTIFS(TestCase!$G:$G,$B$12,TestCase!$K:$K,G8) -> 0 | H12: =COUNTIFS(TestCase!$G:$G,$B$12,TestCase!$K:$K,H8) -> 0 | I12: =COUNTIFS(TestCase!$G:$G,$B$12,TestCase!$K:$K,I8) -> 0
B13: Not Completed | C13: =COUNTIFS(TestCase!$G:$G,$B$13,TestCase!$K:$K,C8) -> 0 | D13: =COUNTIFS(TestCase!$G:$G,$B$13,TestCase!$K:$K,D8) -> 0 | E13: =COUNTIFS(TestCase!$G:$G,$B$13,TestCase!$K:$K,E8) -> 0 | F13: =COUNTIFS(TestCase!$G:$G,$B$13,TestCase!$K:$K,F8) -> 0 | G13: =COUNTIFS(TestCase!$G:$G,$B$13,TestCase!$K:$K,G8) -> 0 | H13: =COUNTIFS(TestCase!$G:$G,$B$13,TestCase!$K:$K,H8) -> 0 | I13: =COUNTIFS(TestCase!$G:$G,$B$13,TestCase!$K:$K,I8) -> 0
B14: Actual execution | C14: =SUM(C9:C13) -> 0 | D14: =SUM(D9:D13) -> 0 | E14: =SUM(E9:E13) -> 0 | F14: =SUM(F9:F13) -> 0 | G14: =SUM(G9:G13) -> 0 | H14: =SUM(H9:H13) -> 0 | I14: =SUM(I9:I13) -> 0
B15: Not yet execution | C15: =$C$5-C14 -> 212 | D15: =C15-D14 -> 212 | E15: =D15-E14 -> 212 | F15: =E15-F14 -> 212 | G15: =F15-G14 -> 212 | H15: =G15-H14 -> 212 | I15: =H15-I14 -> 212
B17: Execute test case lần 2 theo ngày
B18: Date Status | C18: 43374 | D18: 43375 | E18: 43376 | F18: 43377 | G18: 43378 | H18: 43379 | I18: 43380
B19: Pass | C19: =COUNTIFS(TestCase!$G:$G,$B$19,TestCase!$K:$K,C18) -> 0 | D19: =COUNTIFS(TestCase!$G:$G,$B$19,TestCase!$K:$K,D18) -> 0 | E19: =COUNTIFS(TestCase!$G:$G,$B$19,TestCase!$K:$K,E18) -> 0 | F19: =COUNTIFS(TestCase!$G:$G,$B$19,TestCase!$K:$K,F18) -> 0 | G19: =COUNTIFS(TestCase!$G:$G,$B$19,TestCase!$K:$K,G18) -> 0 | H19: =COUNTIFS(TestCase!$G:$G,$B$19,TestCase!$K:$K,H18) -> 0 | I19: =COUNTIFS(TestCase!$G:$G,$B$19,TestCase!$K:$K,I18) -> 0
B20: Fail | C20: =COUNTIFS(TestCase!$G:$G,$B$20,TestCase!$K:$K,C18) -> 0 | D20: =COUNTIFS(TestCase!$G:$G,$B$20,TestCase!$K:$K,D18) -> 0 | E20: =COUNTIFS(TestCase!$G:$G,$B$20,TestCase!$K:$K,E18) -> 0 | F20: =COUNTIFS(TestCase!$G:$G,$B$20,TestCase!$K:$K,F18) -> 0 | G20: =COUNTIFS(TestCase!$G:$G,$B$20,TestCase!$K:$K,G18) -> 0 | H20: =COUNTIFS(TestCase!$G:$G,$B$20,TestCase!$K:$K,H18) -> 0 | I20: =COUNTIFS(TestCase!$G:$G,$B$20,TestCase!$K:$K,I18) -> 0
B21: Block | C21: =COUNTIFS(TestCase!$G:$G,$B$21,TestCase!$K:$K,C18) -> 0 | D21: =COUNTIFS(TestCase!$G:$G,$B$21,TestCase!$K:$K,D18) -> 0 | E21: =COUNTIFS(TestCase!$G:$G,$B$21,TestCase!$K:$K,E18) -> 0 | F21: =COUNTIFS(TestCase!$G:$G,$B$21,TestCase!$K:$K,F18) -> 0 | G21: =COUNTIFS(TestCase!$G:$G,$B$21,TestCase!$K:$K,G18) -> 0 | H21: =COUNTIFS(TestCase!$G:$G,$B$21,TestCase!$K:$K,H18) -> 0 | I21: =COUNTIFS(TestCase!$G:$G,$B$21,TestCase!$K:$K,I18) -> 0
B22: Pending | C22: =COUNTIFS(TestCase!$G:$G,$B$22,TestCase!$K:$K,C18) -> 0 | D22: =COUNTIFS(TestCase!$G:$G,$B$22,TestCase!$K:$K,D18) -> 0 | E22: =COUNTIFS(TestCase!$G:$G,$B$22,TestCase!$K:$K,E18) -> 0 | F22: =COUNTIFS(TestCase!$G:$G,$B$22,TestCase!$K:$K,F18) -> 0 | G22: =COUNTIFS(TestCase!$G:$G,$B$22,TestCase!$K:$K,G18) -> 0 | H22: =COUNTIFS(TestCase!$G:$G,$B$22,TestCase!$K:$K,H18) -> 0 | I22: =COUNTIFS(TestCase!$G:$G,$B$22,TestCase!$K:$K,I18) -> 0
B23: Not Completed | C23: =COUNTIFS(TestCase!$G:$G,$B$23,TestCase!$K:$K,C18) -> 0 | D23: =COUNTIFS(TestCase!$G:$G,$B$23,TestCase!$K:$K,D18) -> 0 | E23: =COUNTIFS(TestCase!$G:$G,$B$23,TestCase!$K:$K,E18) -> 0 | F23: =COUNTIFS(TestCase!$G:$G,$B$23,TestCase!$K:$K,F18) -> 0 | G23: =COUNTIFS(TestCase!$G:$G,$B$23,TestCase!$K:$K,G18) -> 0 | H23: =COUNTIFS(TestCase!$G:$G,$B$23,TestCase!$K:$K,H18) -> 0 | I23: =COUNTIFS(TestCase!$G:$G,$B$23,TestCase!$K:$K,I18) -> 0
B24: Actual execution | C24: =SUM(C19:C23) -> 0 | D24: =SUM(D19:D23) -> 0 | E24: =SUM(E19:E23) -> 0 | F24: =SUM(F19:F23) -> 0 | G24: =SUM(G19:G23) -> 0 | H24: =SUM(H19:H23) -> 0 | I24: =SUM(I19:I23) -> 0
B25: Not yet execution | C25: =$C$5-C24 -> 212 | D25: =C25-D24 -> 212 | E25: =D25-E24 -> 212 | F25: =E25-F24 -> 212 | G25: =F25-G24 -> 212 | H25: =G25-H24 -> 212 | I25: =H25-I24 -> 212
B27: Percent execute test case
B28: Percent pass | C28: ='Scenario Test'!K21 -> 0
B29: Percent fail | C29: ='Scenario Test'!L21 -> 0
B30: Percent block | C30: ='Scenario Test'!N21 -> 0
B31: Percent pending | C31: ='Scenario Test'!O21 -> 0
B32: Percent not completed | C32: ='Scenario Test'!P21 -> 0
B33: Percent not run | C33: ='Scenario Test'!M21 -> 1
B35: Execute test case
B36: Pass | C36: ='Scenario Test'!C21 -> 0
B37: Fail | C37: ='Scenario Test'!D21 -> 0
B38: Block | C38: ='Scenario Test'!F21 -> 0
B39: Pending | C39: ='Scenario Test'!G21 -> 0
B40: Not Completed | C40: ='Scenario Test'!H21 -> 0
B41: Not run | C41: ='Scenario Test'!E21 -> 212

Sheet Scenario Test
A3: SUMMARY
A5: Scenario ID | B5: Scenario name | C5: Pass | D5: Fail | E5: + | F5: Block | G5: Pending | H5: Not Completed | I5: - | J5: Total | K5: Percent pass | L5: Percent fail | M5: Percent not run | N5: Percent block | O5: Percent pending | P5: Percent not completed | Q5: Remark
A6: Cash flow
A7: CSH_001 | B7: Cash flow | C7: =COUNTIFS(TestCase!$A:$A,A7,TestCase!$G:$G,$C$5) -> 0 | D7: =COUNTIFS(TestCase!$A:$A,A7,TestCase!$G:$G,$D$5) -> 0 | E7: =COUNTIFS(TestCase!$A:$A,A7,TestCase!$G:$G,$E$5) -> 6 | F7: =COUNTIFS(TestCase!$A:$A,A7,TestCase!$G:$G,$F$5) -> 0 | G7: =COUNTIFS(TestCase!$A:$A,A7,TestCase!$G:$G,$G$5) -> 0 | H7: =COUNTIFS(TestCase!$A:$A,A7,TestCase!$G:$G,$H$5) -> 0 | I7: =COUNTIFS(TestCase!$A:$A,A7,TestCase!$G:$G,$I$5) -> 0 | J7: =SUM(C7:H7) -> 6 | K7: =IFERROR(ROUND(C7/J7,4),0) -> 0 | L7: =IFERROR(ROUND(D7/J7,4),0) -> 0 | M7: =IFERROR(ROUND(E7/J7,4),0) -> 1 | N7: =IFERROR(ROUND(F7/J7,4),0) -> 0 | O7: =IFERROR(ROUND(G7/J7,4),0) -> 0 | P7: =IFERROR(ROUND(H7/J7,4),0) -> 0
A8: CSH_002 | B8: CSH_MOV: Internal cash movement | C8: =COUNTIFS(TestCase!$A:$A,A8,TestCase!$G:$G,$C$5) -> 0 | D8: =COUNTIFS(TestCase!$A:$A,A8,TestCase!$G:$G,$D$5) -> 0 | E8: =COUNTIFS(TestCase!$A:$A,A8,TestCase!$G:$G,$E$5) -> 24 | F8: =COUNTIFS(TestCase!$A:$A,A8,TestCase!$G:$G,$F$5) -> 0 | G8: =COUNTIFS(TestCase!$A:$A,A8,TestCase!$G:$G,$G$5) -> 0 | H8: =COUNTIFS(TestCase!$A:$A,A8,TestCase!$G:$G,$H$5) -> 0 | I8: =COUNTIFS(TestCase!$A:$A,A8,TestCase!$G:$G,$I$5) -> 0 | J8: =SUM(C8:H8) -> 24 | K8: =IFERROR(ROUND(C8/J8,4),0) -> 0 | L8: =IFERROR(ROUND(D8/J8,4),0) -> 0 | M8: =IFERROR(ROUND(E8/J8,4),0) -> 1 | N8: =IFERROR(ROUND(F8/J8,4),0) -> 0 | O8: =IFERROR(ROUND(G8/J8,4),0) -> 0 | P8: =IFERROR(ROUND(H8/J8,4),0) -> 0
A9: CSH_003 | B9: CSH_BMOV: Internal branch cash movement | C9: =COUNTIFS(TestCase!$A:$A,A9,TestCase!$G:$G,$C$5) -> 0 | D9: =COUNTIFS(TestCase!$A:$A,A9,TestCase!$G:$G,$D$5) -> 0 | E9: =COUNTIFS(TestCase!$A:$A,A9,TestCase!$G:$G,$E$5) -> 21 | F9: =COUNTIFS(TestCase!$A:$A,A9,TestCase!$G:$G,$F$5) -> 0 | G9: =COUNTIFS(TestCase!$A:$A,A9,TestCase!$G:$G,$G$5) -> 0 | H9: =COUNTIFS(TestCase!$A:$A,A9,TestCase!$G:$G,$H$5) -> 0 | I9: =COUNTIFS(TestCase!$A:$A,A9,TestCase!$G:$G,$I$5) -> 0 | J9: =SUM(C9:H9) -> 21 | K9: =IFERROR(ROUND(C9/J9,4),0) -> 0 | L9: =IFERROR(ROUND(D9/J9,4),0) -> 0 | M9: =IFERROR(ROUND(E9/J9,4),0) -> 1 | N9: =IFERROR(ROUND(F9/J9,4),0) -> 0 | O9: =IFERROR(ROUND(G9/J9,4),0) -> 0 | P9: =IFERROR(ROUND(H9/J9,4),0) -> 0
A10: CSH_004 | B10: CSH_DNM: Cash denomination | C10: =COUNTIFS(TestCase!$A:$A,A10,TestCase!$G:$G,$C$5) -> 0 | D10: =COUNTIFS(TestCase!$A:$A,A10,TestCase!$G:$G,$D$5) -> 0 | E10: =COUNTIFS(TestCase!$A:$A,A10,TestCase!$G:$G,$E$5) -> 4 | F10: =COUNTIFS(TestCase!$A:$A,A10,TestCase!$G:$G,$F$5) -> 0 | G10: =COUNTIFS(TestCase!$A:$A,A10,TestCase!$G:$G,$G$5) -> 0 | H10: =COUNTIFS(TestCase!$A:$A,A10,TestCase!$G:$G,$H$5) -> 0 | I10: =COUNTIFS(TestCase!$A:$A,A10,TestCase!$G:$G,$I$5) -> 0 | J10: =SUM(C10:H10) -> 4 | K10: =IFERROR(ROUND(C10/J10,4),0) -> 0 | L10: =IFERROR(ROUND(D10/J10,4),0) -> 0 | M10: =IFERROR(ROUND(E10/J10,4),0) -> 1 | N10: =IFERROR(ROUND(F10/J10,4),0) -> 0 | O10: =IFERROR(ROUND(G10/J10,4),0) -> 0 | P10: =IFERROR(ROUND(H10/J10,4),0) -> 0
A11: FX Transaction (F2)
A12: FX_001 | B12: FX Cash-Cash | C12: =COUNTIFS(TestCase!$A:$A,A12,TestCase!$G:$G,$C$5) -> 0 | D12: =COUNTIFS(TestCase!$A:$A,A12,TestCase!$G:$G,$D$5) -> 0 | E12: =COUNTIFS(TestCase!$A:$A,A12,TestCase!$G:$G,$E$5) -> 9 | F12: =COUNTIFS(TestCase!$A:$A,A12,TestCase!$G:$G,$F$5) -> 0 | G12: =COUNTIFS(TestCase!$A:$A,A12,TestCase!$G:$G,$G$5) -> 0 | H12: =COUNTIFS(TestCase!$A:$A,A12,TestCase!$G:$G,$H$5) -> 0 | I12: =COUNTIFS(TestCase!$A:$A,A12,TestCase!$G:$G,$I$5) -> 0 | J12: =SUM(C12:H12) -> 9 | K12: =IFERROR(ROUND(C12/J12,4),0) -> 0 | L12: =IFERROR(ROUND(D12/J12,4),0) -> 0 | M12: =IFERROR(ROUND(E12/J12,4),0) -> 1 | N12: =IFERROR(ROUND(F12/J12,4),0) -> 0 | O12: =IFERROR(ROUND(G12/J12,4),0) -> 0 | P12: =IFERROR(ROUND(H12/J12,4),0) -> 0
A13: FX_002 | B13: FX Cash-Deposit | C13: =COUNTIFS(TestCase!$A:$A,A13,TestCase!$G:$G,$C$5) -> 0 | D13: =COUNTIFS(TestCase!$A:$A,A13,TestCase!$G:$G,$D$5) -> 0 | E13: =COUNTIFS(TestCase!$A:$A,A13,TestCase!$G:$G,$E$5) -> 10 | F13: =COUNTIFS(TestCase!$A:$A,A13,TestCase!$G:$G,$F$5) -> 0 | G13: =COUNTIFS(TestCase!$A:$A,A13,TestCase!$G:$G,$G$5) -> 0 | H13: =COUNTIFS(TestCase!$A:$A,A13,TestCase!$G:$G,$H$5) -> 0 | I13: =COUNTIFS(TestCase!$A:$A,A13,TestCase!$G:$G,$I$5) -> 0 | J13: =SUM(C13:H13) -> 10 | K13: =IFERROR(ROUND(C13/J13,4),0) -> 0 | L13: =IFERROR(ROUND(D13/J13,4),0) -> 0 | M13: =IFERROR(ROUND(E13/J13,4),0) -> 1 | N13: =IFERROR(ROUND(F13/J13,4),0) -> 0 | O13: =IFERROR(ROUND(G13/J13,4),0) -> 0 | P13: =IFERROR(ROUND(H13/J13,4),0) -> 0
A14: FX_003 | B14: FX Cash-GL | C14: =COUNTIFS(TestCase!$A:$A,A14,TestCase!$G:$G,$C$5) -> 0 | D14: =COUNTIFS(TestCase!$A:$A,A14,TestCase!$G:$G,$D$5) -> 0 | E14: =COUNTIFS(TestCase!$A:$A,A14,TestCase!$G:$G,$E$5) -> 16 | F14: =COUNTIFS(TestCase!$A:$A,A14,TestCase!$G:$G,$F$5) -> 0 | G14: =COUNTIFS(TestCase!$A:$A,A14,TestCase!$G:$G,$G$5) -> 0 | H14: =COUNTIFS(TestCase!$A:$A,A14,TestCase!$G:$G,$H$5) -> 0 | I14: =COUNTIFS(TestCase!$A:$A,A14,TestCase!$G:$G,$I$5) -> 0 | J14: =SUM(C14:H14) -> 16 | K14: =IFERROR(ROUND(C14/J14,4),0) -> 0 | L14: =IFERROR(ROUND(D14/J14,4),0) -> 0 | M14: =IFERROR(ROUND(E14/J14,4),0) -> 1 | N14: =IFERROR(ROUND(F14/J14,4),0) -> 0 | O14: =IFERROR(ROUND(G14/J14,4),0) -> 0 | P14: =IFERROR(ROUND(H14/J14,4),0) -> 0
A15: FX_004 | B15: FX Deposit-Cash | C15: =COUNTIFS(TestCase!$A:$A,A15,TestCase!$G:$G,$C$5) -> 0 | D15: =COUNTIFS(TestCase!$A:$A,A15,TestCase!$G:$G,$D$5) -> 0 | E15: =COUNTIFS(TestCase!$A:$A,A15,TestCase!$G:$G,$E$5) -> 16 | F15: =COUNTIFS(TestCase!$A:$A,A15,TestCase!$G:$G,$F$5) -> 0 | G15: =COUNTIFS(TestCase!$A:$A,A15,TestCase!$G:$G,$G$5) -> 0 | H15: =COUNTIFS(TestCase!$A:$A,A15,TestCase!$G:$G,$H$5) -> 0 | I15: =COUNTIFS(TestCase!$A:$A,A15,TestCase!$G:$G,$I$5) -> 0 | J15: =SUM(C15:H15) -> 16 | K15: =IFERROR(ROUND(C15/J15,4),0) -> 0 | L15: =IFERROR(ROUND(D15/J15,4),0) -> 0 | M15: =IFERROR(ROUND(E15/J15,4),0) -> 1 | N15: =IFERROR(ROUND(F15/J15,4),0) -> 0 | O15: =IFERROR(ROUND(G15/J15,4),0) -> 0 | P15: =IFERROR(ROUND(H15/J15,4),0) -> 0
A16: FX_005 | B16: FX Deposit-Deposit | C16: =COUNTIFS(TestCase!$A:$A,A16,TestCase!$G:$G,$C$5) -> 0 | D16: =COUNTIFS(TestCase!$A:$A,A16,TestCase!$G:$G,$D$5) -> 0 | E16: =COUNTIFS(TestCase!$A:$A,A16,TestCase!$G:$G,$E$5) -> 23 | F16: =COUNTIFS(TestCase!$A:$A,A16,TestCase!$G:$G,$F$5) -> 0 | G16: =COUNTIFS(TestCase!$A:$A,A16,TestCase!$G:$G,$G$5) -> 0 | H16: =COUNTIFS(TestCase!$A:$A,A16,TestCase!$G:$G,$H$5) -> 0 | I16: =COUNTIFS(TestCase!$A:$A,A16,TestCase!$G:$G,$I$5) -> 0 | J16: =SUM(C16:H16) -> 23 | K16: =IFERROR(ROUND(C16/J16,4),0) -> 0 | L16: =IFERROR(ROUND(D16/J16,4),0) -> 0 | M16: =IFERROR(ROUND(E16/J16,4),0) -> 1 | N16: =IFERROR(ROUND(F16/J16,4),0) -> 0 | O16: =IFERROR(ROUND(G16/J16,4),0) -> 0 | P16: =IFERROR(ROUND(H16/J16,4),0) -> 0
A17: FX_006 | B17: FX Deposit-GL | C17: =COUNTIFS(TestCase!$A:$A,A17,TestCase!$G:$G,$C$5) -> 0 | D17: =COUNTIFS(TestCase!$A:$A,A17,TestCase!$G:$G,$D$5) -> 0 | E17: =COUNTIFS(TestCase!$A:$A,A17,TestCase!$G:$G,$E$5) -> 25 | F17: =COUNTIFS(TestCase!$A:$A,A17,TestCase!$G:$G,$F$5) -> 0 | G17: =COUNTIFS(TestCase!$A:$A,A17,TestCase!$G:$G,$G$5) -> 0 | H17: =COUNTIFS(TestCase!$A:$A,A17,TestCase!$G:$G,$H$5) -> 0 | I17: =COUNTIFS(TestCase!$A:$A,A17,TestCase!$G:$G,$I$5) -> 0 | J17: =SUM(C17:H17) -> 25 | K17: =IFERROR(ROUND(C17/J17,4),0) -> 0 | L17: =IFERROR(ROUND(D17/J17,4),0) -> 0 | M17: =IFERROR(ROUND(E17/J17,4),0) -> 1 | N17: =IFERROR(ROUND(F17/J17,4),0) -> 0 | O17: =IFERROR(ROUND(G17/J17,4),0) -> 0 | P17: =IFERROR(ROUND(H17/J17,4),0) -> 0
A18: FX_007 | B18: FX GL-Cash | C18: =COUNTIFS(TestCase!$A:$A,A18,TestCase!$G:$G,$C$5) -> 0 | D18: =COUNTIFS(TestCase!$A:$A,A18,TestCase!$G:$G,$D$5) -> 0 | E18: =COUNTIFS(TestCase!$A:$A,A18,TestCase!$G:$G,$E$5) -> 17 | F18: =COUNTIFS(TestCase!$A:$A,A18,TestCase!$G:$G,$F$5) -> 0 | G18: =COUNTIFS(TestCase!$A:$A,A18,TestCase!$G:$G,$G$5) -> 0 | H18: =COUNTIFS(TestCase!$A:$A,A18,TestCase!$G:$G,$H$5) -> 0 | I18: =COUNTIFS(TestCase!$A:$A,A18,TestCase!$G:$G,$I$5) -> 0 | J18: =SUM(C18:H18) -> 17 | K18: =IFERROR(ROUND(C18/J18,4),0) -> 0 | L18: =IFERROR(ROUND(D18/J18,4),0) -> 0 | M18: =IFERROR(ROUND(E18/J18,4),0) -> 1 | N18: =IFERROR(ROUND(F18/J18,4),0) -> 0 | O18: =IFERROR(ROUND(G18/J18,4),0) -> 0 | P18: =IFERROR(ROUND(H18/J18,4),0) -> 0
A19: FX_008 | B19: FX GL-Deposit | C19: =COUNTIFS(TestCase!$A:$A,A19,TestCase!$G:$G,$C$5) -> 0 | D19: =COUNTIFS(TestCase!$A:$A,A19,TestCase!$G:$G,$D$5) -> 0 | E19: =COUNTIFS(TestCase!$A:$A,A19,TestCase!$G:$G,$E$5) -> 20 | F19: =COUNTIFS(TestCase!$A:$A,A19,TestCase!$G:$G,$F$5) -> 0 | G19: =COUNTIFS(TestCase!$A:$A,A19,TestCase!$G:$G,$G$5) -> 0 | H19: =COUNTIFS(TestCase!$A:$A,A19,TestCase!$G:$G,$H$5) -> 0 | I19: =COUNTIFS(TestCase!$A:$A,A19,TestCase!$G:$G,$I$5) -> 0 | J19: =SUM(C19:H19) -> 20 | K19: =IFERROR(ROUND(C19/J19,4),0) -> 0 | L19: =IFERROR(ROUND(D19/J19,4),0) -> 0 | M19: =IFERROR(ROUND(E19/J19,4),0) -> 1 | N19: =IFERROR(ROUND(F19/J19,4),0) -> 0 | O19: =IFERROR(ROUND(G19/J19,4),0) -> 0 | P19: =IFERROR(ROUND(H19/J19,4),0) -> 0
A20: FX_009 | B20: FX GL-GL | C20: =COUNTIFS(TestCase!$A:$A,A20,TestCase!$G:$G,$C$5) -> 0 | D20: =COUNTIFS(TestCase!$A:$A,A20,TestCase!$G:$G,$D$5) -> 0 | E20: =COUNTIFS(TestCase!$A:$A,A20,TestCase!$G:$G,$E$5) -> 21 | F20: =COUNTIFS(TestCase!$A:$A,A20,TestCase!$G:$G,$F$5) -> 0 | G20: =COUNTIFS(TestCase!$A:$A,A20,TestCase!$G:$G,$G$5) -> 0 | H20: =COUNTIFS(TestCase!$A:$A,A20,TestCase!$G:$G,$H$5) -> 0 | I20: =COUNTIFS(TestCase!$A:$A,A20,TestCase!$G:$G,$I$5) -> 0 | J20: =SUM(C20:H20) -> 21 | K20: =IFERROR(ROUND(C20/J20,4),0) -> 0 | L20: =IFERROR(ROUND(D20/J20,4),0) -> 0 | M20: =IFERROR(ROUND(E20/J20,4),0) -> 1 | N20: =IFERROR(ROUND(F20/J20,4),0) -> 0 | O20: =IFERROR(ROUND(G20/J20,4),0) -> 0 | P20: =IFERROR(ROUND(H20/J20,4),0) -> 0
A21: Total | C21: =SUM(C7:C20) -> 0 | D21: =SUM(D7:D20) -> 0 | E21: =SUM(E7:E20) -> 212 | F21: =SUM(F7:F20) -> 0 | G21: =SUM(G7:G20) -> 0 | H21: =SUM(H7:H20) -> 0 | I21: =SUM(I7:I20) -> 0 | J21: =SUM(J7:J20) -> 212 | K21: =IFERROR(100%-SUM(L21:P21),0) -> 0 | L21: =IFERROR(ROUND(D21/$J$21,4),0) -> 0 | M21: =IFERROR(ROUND(E21/$J$21,4),0) -> 1 | N21: =IFERROR(ROUND(F21/$J$21,4),0) -> 0 | O21: =IFERROR(ROUND(G21/$J$21,4),0) -> 0 | P21: =IFERROR(ROUND(H21/$J$21,4),0) -> 0
A23: Remark: Status of Test Scenario on section “Overall Status”:
A24: - Passed = Test Scenario has been tested as planned and application works as expected result.
A25: - Failed = Test Scenario has been tested as planned but application does not work as expected.
A26: - Blocked = Test Scenario could not be tested as planned because there is an outstanding defect in related function area.
A27: - Not Completed = Test Scenario has been tested as planned but not yet finished due to awaiting test result (ex: require EOD batch).
A28: - No Run (+) = Test Scenario has not been tested as planned.
A29: - Pending = Test Scenario will be tested after confirming about the business.
A30: - Cancel (-) = Test Scenario could not be tested because of wrong condition, not suitable with the environment.

Sheet TestCase
A2: TEST CASES
A3: Environment:
A5: Scenario ID | B5: Scenario name | C5: Test case ID | D5: Test condition ID | E5: Condition | F5: Expected Result | G5: Result | H5: Comments | I5: Create date | J5: Test lần 1 | K5: Test lần 2 | L5: Executor | M5: Editor | N5: Update date
A6: ='Scenario Test'!$A$7 -> CSH_001 | B6: =VLOOKUP(TestCase!A6,'Scenario Test'!$A$5:$B$117,2,0) -> Cash flow
A7: ='Scenario Test'!$A$7 -> CSH_001 | B7: =VLOOKUP(TestCase!A7,'Scenario Test'!$A$5:$B$117,2,0) -> Cash flow | C7: CSH_001_001 | E7: Open "Cash flow" screen by shortcut "Ctrl + F7" | F7: View successfully | G7: + | I7: 45642
A8: ='Scenario Test'!$A$7 -> CSH_001 | B8: =VLOOKUP(TestCase!A8,'Scenario Test'!$A$5:$B$117,2,0) -> Cash flow | C8: CSH_001_002 | E8: Open "Cash flow" screen by quickly search | F8: View successfully | G8: + | I8: 45642
A9: ='Scenario Test'!$A$7 -> CSH_001 | B9: =VLOOKUP(TestCase!A9,'Scenario Test'!$A$5:$B$117,2,0) -> Cash flow | C9: CSH_001_003 | E9: View "Cash flow" with user has only position "Cashier" | F9: View successfully | G9: + | I9: 45642
A10: ='Scenario Test'!$A$7 -> CSH_001 | B10: =VLOOKUP(TestCase!A10,'Scenario Test'!$A$5:$B$117,2,0) -> Cash flow | C10: CSH_001_004 | E10: View "Cash flow" with user has position "Chief Cashier" | F10: View successfully | G10: + | I10: 45642
A11: ='Scenario Test'!$A$7 -> CSH_001 | B11: =VLOOKUP(TestCase!A11,'Scenario Test'!$A$5:$B$117,2,0) -> Cash flow | C11: CSH_001_005 | E11: Make transaction increase cash | F11: Update Customer deposit, Total In, Closing balance | G11: + | I11: 45642
A12: ='Scenario Test'!$A$7 -> CSH_001 | B12: =VLOOKUP(TestCase!A12,'Scenario Test'!$A$5:$B$117,2,0) -> Cash flow | C12: CSH_001_006 | E12: Make transaction decrease cash | F12: Update Customer withdrawal, Total Out, Closing balance | G12: + | I12: 45642
A13: ='Scenario Test'!$A$8 -> CSH_002 | B13: =VLOOKUP(TestCase!A13,'Scenario Test'!$A$5:$B$117,2,0) -> CSH_MOV: Internal cash movement
A14: ='Scenario Test'!$A$8 -> CSH_002 | B14: =VLOOKUP(TestCase!A14,'Scenario Test'!$A$5:$B$117,2,0) -> CSH_MOV: Internal cash movement | C14: CSH_002_001 | E14: From teller - Position: Cashier - Account status: Active - 0 < Amount <= Closing balance To teller code - Position: Chief Cashier - Account status: Active - Branch of "To teller" = Branch of "From teller" 1. Open "Internal Cash Movement" screen 2. Choose To teller code 3. Input Amount 4. Choose currency 5. Click accept | F14: System shows popup approve | G14: + | I14: 45637
A15: ='Scenario Test'!$A$8 -> CSH_002 | B15: =VLOOKUP(TestCase!A15,'Scenario Test'!$A$5:$B$117,2,0) -> CSH_MOV: Internal cash movement | C15: CSH_002_002 | D15: =C14 -> CSH_002_001 | E15: Approver = Receiver | F15: Transaction successfully | G15: + | I15: 45637
A16: ='Scenario Test'!$A$8 -> CSH_002 | B16: =VLOOKUP(TestCase!A16,'Scenario Test'!$A$5:$B$117,2,0) -> CSH_MOV: Internal cash movement | C16: CSH_002_003 | E16: To teller code is empty | F16: Transaction fail | G16: + | I16: 45637
A17: ='Scenario Test'!$A$8 -> CSH_002 | B17: =VLOOKUP(TestCase!A17,'Scenario Test'!$A$5:$B$117,2,0) -> CSH_MOV: Internal cash movement | C17: CSH_002_004 | E17: To teller code does not exist | F17: Transaction fail | G17: + | I17: 45637
A18: ='Scenario Test'!$A$8 -> CSH_002 | B18: =VLOOKUP(TestCase!A18,'Scenario Test'!$A$5:$B$117,2,0) -> CSH_MOV: Internal cash movement | C18: CSH_002_005 | E18: Amount <= 0 | F18: Transaction fail | G18: + | I18: 45637
A19: ='Scenario Test'!$A$8 -> CSH_002 | B19: =VLOOKUP(TestCase!A19,'Scenario Test'!$A$5:$B$117,2,0) -> CSH_MOV: Internal cash movement | C19: CSH_002_006 | E19: From teller - Position: Chief Cashier - Account status: Active - 0 < Amount <= Closing balance To teller code - Position: Chief Cashier - Account status: Active - Branch of "To teller" = Branch of "From teller" | F19: System shows popup approve | G19: + | I19: 45637
A20: ='Scenario Test'!$A$8 -> CSH_002 | B20: =VLOOKUP(TestCase!A20,'Scenario Test'!$A$5:$B$117,2,0) -> CSH_MOV: Internal cash movement | C20: CSH_002_007 | D20: =C19 -> CSH_002_006 | E20: Approver = Receiver | F20: Transaction fail | G20: + | I20: 45637
A21: ='Scenario Test'!$A$8 -> CSH_002 | B21: =VLOOKUP(TestCase!A21,'Scenario Test'!$A$5:$B$117,2,0) -> CSH_MOV: Internal cash movement | C21: CSH_002_008 | E21: From teller - Position: Cashier and Chief Cashier - Account status: Active - 0 < Amount <= Closing balance To teller code - Position: Chief Cashier - Account status: Active - Branch of "To teller" = Branch of "From teller" | F21: System shows popup approve | G21: + | I21: 45637
A22: ='Scenario Test'!$A$8 -> CSH_002 | B22: =VLOOKUP(TestCase!A22,'Scenario Test'!$A$5:$B$117,2,0) -> CSH_MOV: Internal cash movement | C22: CSH_002_009 | D22: =C21 -> CSH_002_008 | E22: Approver = Receiver | F22: Transaction fail | G22: + | I22: 45637
A23: ='Scenario Test'!$A$8 -> CSH_002 | B23: =VLOOKUP(TestCase!A23,'Scenario Test'!$A$5:$B$117,2,0) -> CSH_MOV: Internal cash movement | C23: CSH_002_010 | E23: From teller - Position: Cashier - Account status <> Active - 0 < Amount <= Closing balance To teller code - Position: Chief Cashier - Account status: Active - Branch of "To teller" = Branch of "From teller" | F23: System shows popup approve | G23: + | I23: 45637
A24: ='Scenario Test'!$A$8 -> CSH_002 | B24: =VLOOKUP(TestCase!A24,'Scenario Test'!$A$5:$B$117,2,0) -> CSH_MOV: Internal cash movement | C24: CSH_002_011 | D24: =C23 -> CSH_002_010 | E24: Approver = Receiver | F24: Transaction fail | G24: + | H24: check theo hiện trạng trên prod đang không validate | I24: 45637
A25: ='Scenario Test'!$A$8 -> CSH_002 | B25: =VLOOKUP(TestCase!A25,'Scenario Test'!$A$5:$B$117,2,0) -> CSH_MOV: Internal cash movement | C25: CSH_002_012 | E25: From teller - Position: Cashier - Account status: Active - Amount > Closing balance To teller code - Position: Chief Cashier - Account status: Active - Branch of "To teller" = Branch of "From teller" | F25: System shows popup approve | G25: + | I25: 45637
A26: ='Scenario Test'!$A$8 -> CSH_002 | B26: =VLOOKUP(TestCase!A26,'Scenario Test'!$A$5:$B$117,2,0) -> CSH_MOV: Internal cash movement | C26: CSH_002_013 | D26: =C25 -> CSH_002_012 | E26: Approver = Receiver | F26: Transaction fail | G26: + | I26: 45637
A27: ='Scenario Test'!$A$8 -> CSH_002 | B27: =VLOOKUP(TestCase!A27,'Scenario Test'!$A$5:$B$117,2,0) -> CSH_MOV: Internal cash movement | C27: CSH_002_014 | E27: From teller - Position: Cashier - Account status: Active - 0 < Amount <= Closing balance To teller code - Position: Cashier - Account status: Active - Branch of "To teller" = Branch of "From teller" | F27: System shows popup approve | G27: + | I27: 45637
A28: ='Scenario Test'!$A$8 -> CSH_002 | B28: =VLOOKUP(TestCase!A28,'Scenario Test'!$A$5:$B$117,2,0) -> CSH_MOV: Internal cash movement | C28: CSH_002_015 | D28: =C27 -> CSH_002_014 | E28: Approver = Receiver | F28: Transaction fail | G28: + | I28: 45637
A29: ='Scenario Test'!$A$8 -> CSH_002 | B29: =VLOOKUP(TestCase!A29,'Scenario Test'!$A$5:$B$117,2,0) -> CSH_MOV: Internal cash movement | C29: CSH_002_016 | E29: From teller - Position: Cashier - Account status: Active - 0 < Amount <= Closing balance To teller code - Position: Chief Cashier and Cashier - Account status: Active - Branch of "To teller" = Branch of "From teller" | F29: System shows popup approve | G29: + | I29: 45637
A30: ='Scenario Test'!$A$8 -> CSH_002 | B30: =VLOOKUP(TestCase!A30,'Scenario Test'!$A$5:$B$117,2,0) -> CSH_MOV: Internal cash movement | C30: CSH_002_017 | D30: =C29 -> CSH_002_016 | E30: Approver = Receiver | F30: Transaction fail | G30: + | I30: 45637
A31: ='Scenario Test'!$A$8 -> CSH_002 | B31: =VLOOKUP(TestCase!A31,'Scenario Test'!$A$5:$B$117,2,0) -> CSH_MOV: Internal cash movement | C31: CSH_002_018 | E31: From teller - Position: Cashier - Account status: Active - 0 < Amount <= Closing balance To teller code - Position: Chief Cashier - Account status <> Active - Branch of "To teller" = Branch of "From teller" | F31: System shows popup approve | G31: + | I31: 45637
A32: ='Scenario Test'!$A$8 -> CSH_002 | B32: =VLOOKUP(TestCase!A32,'Scenario Test'!$A$5:$B$117,2,0) -> CSH_MOV: Internal cash movement | C32: CSH_002_019 | D32: =C31 -> CSH_002_018 | E32: Approver = Receiver | F32: Transaction fail | G32: + | I32: 45637
A33: ='Scenario Test'!$A$8 -> CSH_002 | B33: =VLOOKUP(TestCase!A33,'Scenario Test'!$A$5:$B$117,2,0) -> CSH_MOV: Internal cash movement | C33: CSH_002_020 | E33: From teller - Position: Cashier - Account status: Active - 0 < Amount <= Closing balance To teller code - Position: Chief Cashier - Account status: Active - Branch of "To teller" <> Branch of "From teller" | F33: System shows popup approve | G33: + | I33: 45637
A34: ='Scenario Test'!$A$8 -> CSH_002 | B34: =VLOOKUP(TestCase!A34,'Scenario Test'!$A$5:$B$117,2,0) -> CSH_MOV: Internal cash movement | C34: CSH_002_021 | D34: =C33 -> CSH_002_020 | E34: Approver = Receiver | F34: Transaction fail | G34: + | I34: 45637
A35: ='Scenario Test'!$A$8 -> CSH_002 | B35: =VLOOKUP(TestCase!A35,'Scenario Test'!$A$5:$B$117,2,0) -> CSH_MOV: Internal cash movement | C35: CSH_002_022 | E35: From teller - Position: Cashier - Account status: Active - 0 < Amount <= Closing balance To teller code - Position: Chief Cashier - Account status: Active - Branch of "To teller" = Branch of "From teller" | F35: System shows popup approve | G35: + | I35: 45637
A36: ='Scenario Test'!$A$8 -> CSH_002 | B36: =VLOOKUP(TestCase!A36,'Scenario Test'!$A$5:$B$117,2,0) -> CSH_MOV: Internal cash movement | C36: CSH_002_023 | D36: =C35 -> CSH_002_022 | E36: Approver <> Receiver | F36: Transaction fail | G36: + | I36: 45637
A37: ='Scenario Test'!$A$8 -> CSH_002 | B37: =VLOOKUP(TestCase!A37,'Scenario Test'!$A$5:$B$117,2,0) -> CSH_MOV: Internal cash movement | C37: CSH_002_024 | E37: Reverse transaction | F37: Transaction successfully | G37: + | I37: 45637
A38: ='Scenario Test'!$A$9 -> CSH_003 | B38: =VLOOKUP(TestCase!A38,'Scenario Test'!$A$5:$B$117,2,0) -> CSH_BMOV: Internal branch cash movement
A39: ='Scenario Test'!$A$9 -> CSH_003 | B39: =VLOOKUP(TestCase!A39,'Scenario Test'!$A$5:$B$117,2,0) -> CSH_BMOV: Internal branch cash movement | C39: CSH_003_001 | E39: From teller - Position Chief Cashier - Account status: Active - 0 < Amount <= Closing balance To teller code - Position: Chief Cashier - Account status: Active - Branch of "To teller" <> Branch of "From teller" 1. Open "Internal Branch Cash Movement" screen 2. Choose Send to branch 3. Choose To teller code 4. Input Amount 5. Choose currency 6. Click accept | F39: System shows popup approve | G39: + | I39: 45638
A40: ='Scenario Test'!$A$9 -> CSH_003 | B40: =VLOOKUP(TestCase!A40,'Scenario Test'!$A$5:$B$117,2,0) -> CSH_BMOV: Internal branch cash movement | C40: CSH_003_002 | D40: =C39 -> CSH_003_001 | E40: Approver = Receiver | F40: Transaction successfully | G40: + | I40: 45638
A41: ='Scenario Test'!$A$9 -> CSH_003 | B41: =VLOOKUP(TestCase!A41,'Scenario Test'!$A$5:$B$117,2,0) -> CSH_BMOV: Internal branch cash movement | C41: CSH_003_003 | E41: To teller code is empty | F41: Transaction fail | G41: + | I41: 45638
A42: ='Scenario Test'!$A$9 -> CSH_003 | B42: =VLOOKUP(TestCase!A42,'Scenario Test'!$A$5:$B$117,2,0) -> CSH_BMOV: Internal branch cash movement | C42: CSH_003_004 | E42: To teller code does not exist | F42: Transaction fail | G42: + | I42: 45638
A43: ='Scenario Test'!$A$9 -> CSH_003 | B43: =VLOOKUP(TestCase!A43,'Scenario Test'!$A$5:$B$117,2,0) -> CSH_BMOV: Internal branch cash movement | C43: CSH_003_005 | E43: Amount <= 0 | F43: Transaction fail | G43: + | I43: 45638
A44: ='Scenario Test'!$A$9 -> CSH_003 | B44: =VLOOKUP(TestCase!A44,'Scenario Test'!$A$5:$B$117,2,0) -> CSH_BMOV: Internal branch cash movement | C44: CSH_003_006 | E44: From teller - Position <> Chief Cashier - Account status: Active - 0 < Amount <= Closing balance To teller code - Position: Chief Cashier - Account status: Active - Branch of "To teller" <> Branch of "From teller" | F44: System shows popup approve | G44: + | I44: 45638
A45: ='Scenario Test'!$A$9 -> CSH_003 | B45: =VLOOKUP(TestCase!A45,'Scenario Test'!$A$5:$B$117,2,0) -> CSH_BMOV: Internal branch cash movement | C45: CSH_003_007 | D45: =C44 -> CSH_003_006 | E45: Approver = Receiver | F45: Transaction fail | G45: + | I45: 45638
A46: ='Scenario Test'!$A$9 -> CSH_003 | B46: =VLOOKUP(TestCase!A46,'Scenario Test'!$A$5:$B$117,2,0) -> CSH_BMOV: Internal branch cash movement | C46: CSH_003_008 | E46: From teller - Position: Chief Cashier - Account status <> Active - 0 < Amount <= Closing balance To teller code - Position: Chief Cashier - Account status: Active - Branch of "To teller" <> Branch of "From teller" | F46: System shows popup approve | G46: + | I46: 45638
A47: ='Scenario Test'!$A$9 -> CSH_003 | B47: =VLOOKUP(TestCase!A47,'Scenario Test'!$A$5:$B$117,2,0) -> CSH_BMOV: Internal branch cash movement | C47: CSH_003_009 | D47: =C46 -> CSH_003_008 | E47: Approver = Receiver | F47: Transaction fail | G47: + | I47: 45638
A48: ='Scenario Test'!$A$9 -> CSH_003 | B48: =VLOOKUP(TestCase!A48,'Scenario Test'!$A$5:$B$117,2,0) -> CSH_BMOV: Internal branch cash movement | C48: CSH_003_010 | E48: From teller - Position: Chief Cashier - Account status: Active - Amount > Closing balance To teller code - Position: Chief Cashier - Account status: Active - Branch of "To teller" <> Branch of "From teller" | F48: System shows popup approve | G48: + | I48: 45638
A49: ='Scenario Test'!$A$9 -> CSH_003 | B49: =VLOOKUP(TestCase!A49,'Scenario Test'!$A$5:$B$117,2,0) -> CSH_BMOV: Internal branch cash movement | C49: CSH_003_011 | D49: =C48 -> CSH_003_010 | E49: Approver = Receiver | F49: Transaction fail | G49: + | I49: 45638
A50: ='Scenario Test'!$A$9 -> CSH_003 | B50: =VLOOKUP(TestCase!A50,'Scenario Test'!$A$5:$B$117,2,0) -> CSH_BMOV: Internal branch cash movement | C50: CSH_003_012 | E50: From teller - Position: Chief Cashier - Account status: Active - 0 < Amount <= Closing balance To teller code - Position <> Chief Cashier - Account status: Active - Branch of "To teller" <> Branch of "From teller" | F50: System shows popup approve | G50: + | I50: 45638
A51: ='Scenario Test'!$A$9 -> CSH_003 | B51: =VLOOKUP(TestCase!A51,'Scenario Test'!$A$5:$B$117,2,0) -> CSH_BMOV: Internal branch cash movement | C51: CSH_003_013 | D51: =C50 -> CSH_003_012 | E51: Approver = Receiver | F51: Transaction fail | G51: + | I51: 45638
A52: ='Scenario Test'!$A$9 -> CSH_003 | B52: =VLOOKUP(TestCase!A52,'Scenario Test'!$A$5:$B$117,2,0) -> CSH_BMOV: Internal branch cash movement | C52: CSH_003_014 | E52: From teller - Position: Chief Cashier - Account status: Active - 0 < Amount <= Closing balance To teller code - Position: Chief Cashier - Account status <> Active - Branch of "To teller" <> Branch of "From teller" | F52: System shows popup approve | G52: + | I52: 45638
A53: ='Scenario Test'!$A$9 -> CSH_003 | B53: =VLOOKUP(TestCase!A53,'Scenario Test'!$A$5:$B$117,2,0) -> CSH_BMOV: Internal branch cash movement | C53: CSH_003_015 | D53: =C52 -> CSH_003_014 | E53: Approver = Receiver | F53: Transaction fail | G53: + | I53: 45638
A54: ='Scenario Test'!$A$9 -> CSH_003 | B54: =VLOOKUP(TestCase!A54,'Scenario Test'!$A$5:$B$117,2,0) -> CSH_BMOV: Internal branch cash movement | C54: CSH_003_016 | E54: From teller - Position: Chief Cashier - Account status: Active - 0 < Amount <= Closing balance To teller code - Position: Chief Cashier - Account status: Active - Branch of "To teller" = Branch of "From teller" | F54: System shows popup approve | G54: + | I54: 45638
A55: ='Scenario Test'!$A$9 -> CSH_003 | B55: =VLOOKUP(TestCase!A55,'Scenario Test'!$A$5:$B$117,2,0) -> CSH_BMOV: Internal branch cash movement | C55: CSH_003_017 | D55: =C54 -> CSH_003_016 | E55: Approver = Receiver | F55: Transaction fail | G55: + | I55: 45638
A56: ='Scenario Test'!$A$9 -> CSH_003 | B56: =VLOOKUP(TestCase!A56,'Scenario Test'!$A$5:$B$117,2,0) -> CSH_BMOV: Internal branch cash movement | C56: CSH_003_018 | E56: From teller - Position: Chief Cashier - Account status: Active - 0 < Amount <= Closing balance To teller code - Position: Chief Cashier - Account status: Active - Branch of "To teller" <> Branch of "From teller" | F56: System shows popup approve | G56: + | I56: 45638
A57: ='Scenario Test'!$A$9 -> CSH_003 | B57: =VLOOKUP(TestCase!A57,'Scenario Test'!$A$5:$B$117,2,0) -> CSH_BMOV: Internal branch cash movement | C57: CSH_003_019 | D57: =C56 -> CSH_003_018 | E57: Approver <> Receiver | F57: Transaction fail | G57: + | I57: 45638
A58: ='Scenario Test'!$A$9 -> CSH_003 | B58: =VLOOKUP(TestCase!A58,'Scenario Test'!$A$5:$B$117,2,0) -> CSH_BMOV: Internal branch cash movement | C58: CSH_003_020 | E58: Reverse transaction | F58: Transaction successfully | G58: + | I58: 45638
A59: ='Scenario Test'!$A$10 -> CSH_004 | B59: =VLOOKUP(TestCase!A59,'Scenario Test'!$A$5:$B$117,2,0) -> CSH_DNM: Cash denomination
A60: ='Scenario Test'!$A$10 -> CSH_004 | B60: =VLOOKUP(TestCase!A60,'Scenario Test'!$A$5:$B$117,2,0) -> CSH_DNM: Cash denomination | C60: CSH_004_001 | E60: Remaining cash balance > 0 Total Amount > 0 1. Open "Cash denomination" screen 2. Input Sheet 3. Click accept | F60: Transaction successfully | G60: + | I60: 45638
A61: ='Scenario Test'!$A$10 -> CSH_004 | B61: =VLOOKUP(TestCase!A61,'Scenario Test'!$A$5:$B$117,2,0) -> CSH_DNM: Cash denomination | C61: CSH_004_002 | E61: Remaining cash balance = 0 Total Amount > 0 1. Open "Cash denomination" screen 2. Input Sheet 3. Click accept | F61: Transaction successfully | G61: + | I61: 45638
A62: ='Scenario Test'!$A$10 -> CSH_004 | B62: =VLOOKUP(TestCase!A62,'Scenario Test'!$A$5:$B$117,2,0) -> CSH_DNM: Cash denomination | C62: CSH_004_003 | E62: Remaining cash balance < 0 Total Amount > 0 | F62: Transaction fail | G62: + | I62: 45638
A63: ='Scenario Test'!$A$10 -> CSH_004 | B63: =VLOOKUP(TestCase!A63,'Scenario Test'!$A$5:$B$117,2,0) -> CSH_DNM: Cash denomination | C63: CSH_004_004 | E63: Remaining cash balance > 0 Total Amount = 0 | F63: Transaction fail | G63: + | I63: 45638
A64: ='Scenario Test'!$A$9 -> CSH_003 | B64: =VLOOKUP(TestCase!A64,'Scenario Test'!$A$5:$B$117,2,0) -> CSH_BMOV: Internal branch cash movement | C64: CSH_003_020 | E64: Reverse transaction | F64: Do not allow to reverse | G64: + | I64: 45638
A65: ='Scenario Test'!$A$12 -> FX_001 | B65: =VLOOKUP(TestCase!A65,'Scenario Test'!$A$5:$B$117,2,0) -> FX Cash-Cash
A66: ='Scenario Test'!$A$12 -> FX_001 | B66: =VLOOKUP(TestCase!A66,'Scenario Test'!$A$5:$B$117,2,0) -> FX Cash-Cash | C66: FX_001_001 | E66: Debit side - Accounting type: Cash - Debit amount > 0 Credit side - Accounting type: Cash - Credit amount > 0 Teller does this transaction - User has right to do transaction related to cash - User has enough cash to withdraw Debit currency = Credit currency = Base currency 1. Open "FX Transaction" screen 2. Choose Accounting type from Debit 3. Input Debit amount 4. Choose Accounting type from Credit 5. Input Credit amount 6. Click accpet | F66: Transaction successfully | G66: + | I66: 45636
A67: ='Scenario Test'!$A$12 -> FX_001 | B67: =VLOOKUP(TestCase!A67,'Scenario Test'!$A$5:$B$117,2,0) -> FX Cash-Cash | C67: FX_001_002 | E67: Debit side - Accounting type: Cash - Debit amount > 0 Credit side - Accounting type: Cash - Credit amount > 0 Teller does this transaction - User has right to do transaction related to cash - User has enough cash to withdraw Debit currency = Base currency <> Credit currency 1. Open "FX Transaction" screen 2. Choose Accounting type from Debit 3. Input Debit amount 4. Choose Accounting type from Credit 5. Input Credit amount 6. Click accpet | F67: Transaction successfully | G67: + | I67: 45636
A68: ='Scenario Test'!$A$12 -> FX_001 | B68: =VLOOKUP(TestCase!A68,'Scenario Test'!$A$5:$B$117,2,0) -> FX Cash-Cash | C68: FX_001_003 | E68: Debit side - Accounting type: Cash - Debit amount > 0 Credit side - Accounting type: Cash - Credit amount > 0 Teller does this transaction - User has right to do transaction related to cash - User has enough cash to withdraw Debit currency <> Credit currency = Base currency 1. Open "FX Transaction" screen 2. Choose Accounting type from Debit 3. Input Debit amount 4. Choose Accounting type from Credit 5. Input Credit amount 6. Click accpet | F68: Transaction successfully | G68: + | I68: 45636
A69: ='Scenario Test'!$A$12 -> FX_001 | B69: =VLOOKUP(TestCase!A69,'Scenario Test'!$A$5:$B$117,2,0) -> FX Cash-Cash | C69: FX_001_004 | E69: Debit side - Accounting type: Cash - Debit amount > 0 Credit side - Accounting type: Cash - Credit amount > 0 Teller does this transaction - User has right to do transaction related to cash - User has enough cash to withdraw Debit currency <> Credit currency 1. Open "FX Transaction" screen 2. Choose Accounting type from Debit 3. Input Debit amount 4. Choose Accounting type from Credit 5. Input Credit amount 6. Click accpet | F69: Transaction successfully | G69: + | I69: 45636
A70: ='Scenario Test'!$A$12 -> FX_001 | B70: =VLOOKUP(TestCase!A70,'Scenario Test'!$A$5:$B$117,2,0) -> FX Cash-Cash | C70: FX_001_005 | E70: Debit side - Accounting type: Cash - Debit amount > 0 Credit side - Accounting type: Cash - Credit amount > 0 Teller does this transaction - User has right to do transaction related to cash - User has enough cash to withdraw Total fee <= Receive amount 1. Open "FX Transaction" screen 2. Choose Accounting type from Debit 3. Input Debit amount 4. Choose Accounting type from Credit 5. Input Credit amount 6. Add fee 7. Click accpet | F70: Transaction successfully | G70: + | I70: 45636
A71: ='Scenario Test'!$A$12 -> FX_001 | B71: =VLOOKUP(TestCase!A71,'Scenario Test'!$A$5:$B$117,2,0) -> FX Cash-Cash | C71: FX_001_006 | E71: Debit amount <= 0 | F71: Transaction fail | I71: 45636
A72: ='Scenario Test'!$A$12 -> FX_001 | B72: =VLOOKUP(TestCase!A72,'Scenario Test'!$A$5:$B$117,2,0) -> FX Cash-Cash | C72: FX_001_007 | E72: Credit amount <= 0 | F72: Transaction fail | I72: 45636
A73: ='Scenario Test'!$A$12 -> FX_001 | B73: =VLOOKUP(TestCase!A73,'Scenario Test'!$A$5:$B$117,2,0) -> FX Cash-Cash | C73: FX_001_008 | E73: Debit side - Accounting type: Cash - Debit amount > 0 Credit side - Accounting type: Cash - Credit amount > 0 Teller does this transaction - User has NO right to do transaction related to cash - User has enough cash to withdraw | F73: Transaction fail | G73: + | I73: 45636
A74: ='Scenario Test'!$A$12 -> FX_001 | B74: =VLOOKUP(TestCase!A74,'Scenario Test'!$A$5:$B$117,2,0) -> FX Cash-Cash | C74: FX_001_009 | E74: Debit side - Accounting type: Cash - Debit amount > 0 Credit side - Accounting type: Cash - Credit amount > 0 Teller does this transaction - User has right to do transaction related to cash - User has NOT enough cash to withdraw | F74: Transaction fail | G74: + | I74: 45636
A75: ='Scenario Test'!$A$12 -> FX_001 | B75: =VLOOKUP(TestCase!A75,'Scenario Test'!$A$5:$B$117,2,0) -> FX Cash-Cash | C75: FX_001_010 | E75: Debit side - Accounting type: Cash - Debit amount > 0 Credit side - Accounting type: Cash - Credit amount > 0 Teller does this transaction - User has right to do transaction related to cash - User has enough cash to withdraw Total fee > Receive amount | F75: Transaction fail | G75: + | I75: 45636
A76: ='Scenario Test'!$A$12 -> FX_001 | B76: =VLOOKUP(TestCase!A76,'Scenario Test'!$A$5:$B$117,2,0) -> FX Cash-Cash | C76: FX_001_011 | E76: Reverse transaction | F76: Transaction successfully | G76: + | I76: 45636
A77: ='Scenario Test'!$A$13 -> FX_002 | B77: =VLOOKUP(TestCase!A77,'Scenario Test'!$A$5:$B$117,2,0) -> FX Cash-Deposit
A78: ='Scenario Test'!$A$13 -> FX_002 | B78: =VLOOKUP(TestCase!A78,'Scenario Test'!$A$5:$B$117,2,0) -> FX Cash-Deposit | C78: FX_002_001 | E78: Debit side - Accounting type: Cash - Debit amount > 0 Credit side - Accounting type: Deposit - Credit amount > 0 - Deposit type: Current/ Saving - Deposit status: Normal Teller does this transaction - User has right to do transaction related to cash Debit currency = Credit currency = Base currency 1. Open "FX Transaction" screen 2. Choose Accounting type from Debit 3. Input Debit amount 4. Choose Accounting type from Credit 5. Input Account number 6. Input Credit amount 7. Click accpet | F78: Transaction successfully | G78: + | I78: 45636
A79: ='Scenario Test'!$A$13 -> FX_002 | B79: =VLOOKUP(TestCase!A79,'Scenario Test'!$A$5:$B$117,2,0) -> FX Cash-Deposit | C79: FX_002_002 | E79: Debit side - Accounting type: Cash - Debit amount > 0 Credit side - Accounting type: Deposit - Credit amount > 0 - Deposit type: Current/ Saving - Deposit status: Normal Teller does this transaction - User has right to do transaction related to cash Debit currency = Base currency <> Credit currency 1. Open "FX Transaction" screen 2. Choose Accounting type from Debit 3. Input Debit amount 4. Choose Accounting type from Credit 5. Input Account number 6. Input Credit amount 7. Click accpet | F79: Transaction successfully | G79: + | I79: 45636
A80: ='Scenario Test'!$A$13 -> FX_002 | B80: =VLOOKUP(TestCase!A80,'Scenario Test'!$A$5:$B$117,2,0) -> FX Cash-Deposit | C80: FX_002_003 | E80: Debit side - Accounting type: Cash - Debit amount > 0 Credit side - Accounting type: Deposit - Credit amount > 0 - Deposit type: Current/ Saving - Deposit status: Normal Teller does this transaction - User has right to do transaction related to cash Debit currency <> Credit currency = Base currency 1. Open "FX Transaction" screen 2. Choose Accounting type from Debit 3. Input Debit amount 4. Choose Accounting type from Credit 5. Input Account number 6. Input Credit amount 7. Click accpet | F80: Transaction successfully | G80: + | I80: 45636
A81: ='Scenario Test'!$A$13 -> FX_002 | B81: =VLOOKUP(TestCase!A81,'Scenario Test'!$A$5:$B$117,2,0) -> FX Cash-Deposit | C81: FX_002_004 | E81: Debit side - Accounting type: Cash - Debit amount > 0 Credit side - Accounting type: Deposit - Credit amount > 0 - Deposit type: Current/ Saving - Deposit status: Normal Teller does this transaction - User has right to do transaction related to cash Debit currency <> Credit currency 1. Open "FX Transaction" screen 2. Choose Accounting type from Debit 3. Input Debit amount 4. Choose Accounting type from Credit 5. Input Account number 6. Input Credit amount 7. Click accpet | F81: Transaction successfully | G81: + | I81: 45636
A82: ='Scenario Test'!$A$13 -> FX_002 | B82: =VLOOKUP(TestCase!A82,'Scenario Test'!$A$5:$B$117,2,0) -> FX Cash-Deposit | C82: FX_002_005 | E82: Debit side - Accounting type: Cash - Debit amount > 0 Credit side - Accounting type: Deposit - Credit amount > 0 - Deposit type: Current/ Saving - Deposit status: Normal Teller does this transaction - User has right to do transaction related to cash Total fee <= Receive amount 1. Open "FX Transaction" screen 2. Choose Accounting type from Debit 3. Input Debit amount 4. Choose Accounting type from Credit 5. Input Account number 6. Input Credit amount 7. Add fee 8. Click accpet | F82: Transaction successfully | G82: + | I82: 45636
A83: ='Scenario Test'!$A$13 -> FX_002 | B83: =VLOOKUP(TestCase!A83,'Scenario Test'!$A$5:$B$117,2,0) -> FX Cash-Deposit | C83: FX_002_006 | E83: Debit amount <= 0 | F83: Transaction fail | I83: 45636
A84: ='Scenario Test'!$A$13 -> FX_002 | B84: =VLOOKUP(TestCase!A84,'Scenario Test'!$A$5:$B$117,2,0) -> FX Cash-Deposit | C84: FX_002_007 | E84: Credit amount <= 0 | F84: Transaction fail | I84: 45636
A85: ='Scenario Test'!$A$13 -> FX_002 | B85: =VLOOKUP(TestCase!A85,'Scenario Test'!$A$5:$B$117,2,0) -> FX Cash-Deposit | C85: FX_002_008 | E85: Credit account is empty | F85: Transaction fail | I85: 45636
A86: ='Scenario Test'!$A$13 -> FX_002 | B86: =VLOOKUP(TestCase!A86,'Scenario Test'!$A$5:$B$117,2,0) -> FX Cash-Deposit | C86: FX_002_009 | E86: Credit account does not exist | F86: Transaction fail | I86: 45636
A87: ='Scenario Test'!$A$13 -> FX_002 | B87: =VLOOKUP(TestCase!A87,'Scenario Test'!$A$5:$B$117,2,0) -> FX Cash-Deposit | C87: FX_002_010 | E87: Debit side - Accounting type: Cash - Debit amount > 0 Credit side - Accounting type: Deposit - Credit amount > 0 - Deposit type: Fixed deposit - Deposit status: Normal Teller does this transaction - User has right to do transaction related to cash | F87: Transaction fail | G87: + | I87: 45636
A88: ='Scenario Test'!$A$13 -> FX_002 | B88: =VLOOKUP(TestCase!A88,'Scenario Test'!$A$5:$B$117,2,0) -> FX Cash-Deposit | C88: FX_002_011 | E88: Debit side - Accounting type: Cash - Debit amount > 0 Credit side - Accounting type: Deposit - Credit amount > 0 - Deposit type: Current/ Saving - Deposit status <> Normal Teller does this transaction - User has right to do transaction related to cash | F88: Transaction fail | G88: + | I88: 45636
A89: ='Scenario Test'!$A$13 -> FX_002 | B89: =VLOOKUP(TestCase!A89,'Scenario Test'!$A$5:$B$117,2,0) -> FX Cash-Deposit | C89: FX_002_012 | E89: Debit side - Accounting type: Cash - Debit amount > 0 Credit side - Accounting type: Deposit - Credit amount > 0 - Deposit type: Current/ Saving - Deposit status: Normal Teller does this transaction - User has NO right to do transaction related to cash | F89: Transaction fail | G89: + | I89: 45636
A90: ='Scenario Test'!$A$13 -> FX_002 | B90: =VLOOKUP(TestCase!A90,'Scenario Test'!$A$5:$B$117,2,0) -> FX Cash-Deposit | C90: FX_002_013 | E90: Debit side - Accounting type: Cash - Debit amount > 0 Credit side - Accounting type: Deposit - Credit amount > 0 - Deposit type: Current/ Saving - Deposit status: Normal Teller does this transaction - User has right to do transaction related to cash Total fee > Receive amount 1. Open "FX Transaction" screen 2. Choose Accounting type from Debit 3. Input Debit amount 4. Choose Accounting type from Credit 6. Input Account number 7. Input Credit amount 8. Add fee 9. Click accpet | F90: Transaction fail | G90: + | I90: 45636
A91: ='Scenario Test'!$A$13 -> FX_002 | B91: =VLOOKUP(TestCase!A91,'Scenario Test'!$A$5:$B$117,2,0) -> FX Cash-Deposit | C91: FX_002_014 | E91: Reverse transaction | F91: Transaction successfully | G91: + | I91: 45636
A92: ='Scenario Test'!$A$14 -> FX_003 | B92: =VLOOKUP(TestCase!A92,'Scenario Test'!$A$5:$B$117,2,0) -> FX Cash-GL
A93: ='Scenario Test'!$A$14 -> FX_003 | B93: =VLOOKUP(TestCase!A93,'Scenario Test'!$A$5:$B$117,2,0) -> FX Cash-GL | C93: FX_003_001 | E93: Debit side - Accounting type: Cash - Debit amount > 0 Credit side - Accounting type: Accounting - Credit amount > 0 - Posting side: Credit/ Both - Account level: 9 - Account group <> Cash - Direct posting: Yes Teller does this transaction - User has right to do transaction related to cash Debit currency = Credit currency = Base currency 1. Open "FX Transaction" screen 2. Choose Accounting type from Debit 3. Input Debit amount 4. Choose Accounting type from Credit 5. Input Account number 6. Input Credit amount 7. Click accpet | F93: Transaction successfully | G93: + | I93: 45636
A94: ='Scenario Test'!$A$14 -> FX_003 | B94: =VLOOKUP(TestCase!A94,'Scenario Test'!$A$5:$B$117,2,0) -> FX Cash-GL | C94: FX_003_002 | E94: Debit side - Accounting type: Cash - Debit amount > 0 Credit side - Accounting type: Accounting - Credit amount > 0 - Posting side: Credit/ Both - Account level: 9 - Account group <> Cash - Direct posting: Yes Teller does this transaction - User has right to do transaction related to cash Debit currency = Base currency <> Credit currency 1. Open "FX Transaction" screen 2. Choose Accounting type from Debit 3. Input Debit amount 4. Choose Accounting type from Credit 5. Input Account number 6. Input Credit amount 7. Click accpet | F94: Transaction successfully | G94: + | I94: 45636
A95: ='Scenario Test'!$A$14 -> FX_003 | B95: =VLOOKUP(TestCase!A95,'Scenario Test'!$A$5:$B$117,2,0) -> FX Cash-GL | C95: FX_003_003 | E95: Debit side - Accounting type: Cash - Debit amount > 0 Credit side - Accounting type: Accounting - Credit amount > 0 - Posting side: Credit/ Both - Account level: 9 - Account group <> Cash - Direct posting: Yes Teller does this transaction - User has right to do transaction related to cash Debit currency <> Credit currency = Base currency 1. Open "FX Transaction" screen 2. Choose Accounting type from Debit 3. Input Debit amount 4. Choose Accounting type from Credit 5. Input Account number 6. Input Credit amount 7. Click accpet | F95: Transaction successfully | G95: + | I95: 45636
A96: ='Scenario Test'!$A$14 -> FX_003 | B96: =VLOOKUP(TestCase!A96,'Scenario Test'!$A$5:$B$117,2,0) -> FX Cash-GL | C96: FX_003_004 | E96: Debit side - Accounting type: Cash - Debit amount > 0 Credit side - Accounting type: Accounting - Credit amount > 0 - Posting side: Credit/ Both - Account level: 9 - Account group <> Cash - Direct posting: Yes Teller does this transaction - User has right to do transaction related to cash Debit currency <> Credit currency 1. Open "FX Transaction" screen 2. Choose Accounting type from Debit 3. Input Debit amount 4. Choose Accounting type from Credit 5. Input Account number 6. Input Credit amount 7. Click accpet | F96: Transaction successfully | G96: + | I96: 45636
A97: ='Scenario Test'!$A$14 -> FX_003 | B97: =VLOOKUP(TestCase!A97,'Scenario Test'!$A$5:$B$117,2,0) -> FX Cash-GL | C97: FX_003_005 | E97: Debit side - Accounting type: Cash - Debit amount > 0 Credit side - Accounting type: Accounting - Credit amount > 0 - Posting side: Credit/ Both - Account level: 9 - Account group <> Cash - Direct posting: Yes Teller does this transaction - User has right to do transaction related to cash Total fee <= Receive amount 1. Open "FX Transaction" screen 2. Choose Accounting type from Debit 3. Input Debit amount 4. Choose Accounting type from Credit 5. Input Account number 6. Input Credit amount 7. Add fee 8. Click accpet | F97: Transaction successfully | G97: + | I97: 45636
A98: ='Scenario Test'!$A$14 -> FX_003 | B98: =VLOOKUP(TestCase!A98,'Scenario Test'!$A$5:$B$117,2,0) -> FX Cash-GL | C98: FX_003_006 | E98: Debit amount <= 0 | F98: Transaction fail | G98: + | I98: 45636
A99: ='Scenario Test'!$A$14 -> FX_003 | B99: =VLOOKUP(TestCase!A99,'Scenario Test'!$A$5:$B$117,2,0) -> FX Cash-GL | C99: FX_003_007 | E99: Credit amount <= 0 | F99: Transaction fail | G99: + | I99: 45636
A100: ='Scenario Test'!$A$14 -> FX_003 | B100: =VLOOKUP(TestCase!A100,'Scenario Test'!$A$5:$B$117,2,0) -> FX Cash-GL | C100: FX_003_008 | E100: Credit account is empty | F100: Transaction fail | G100: + | I100: 45636
A101: ='Scenario Test'!$A$14 -> FX_003 | B101: =VLOOKUP(TestCase!A101,'Scenario Test'!$A$5:$B$117,2,0) -> FX Cash-GL | C101: FX_003_009 | E101: Credit account does not exist | F101: Transaction fail | G101: + | I101: 45636
A102: ='Scenario Test'!$A$14 -> FX_003 | B102: =VLOOKUP(TestCase!A102,'Scenario Test'!$A$5:$B$117,2,0) -> FX Cash-GL | C102: FX_003_010 | E102: Debit side - Accounting type: Cash - Debit amount > 0 Credit side - Accounting type: Accounting - Credit amount > 0 - Posting side: Debit - Account level: 9 - Account group <> Cash - Direct posting: Yes Teller does this transaction - User has right to do transaction related to cash | F102: Transaction fail | G102: + | I102: 45636
...

Sheet UpdateData
A1: Action | B1: Update data | C1: Update related table
C2: o9accounting | E2: o9admin | G2: o9cash | I2: o9deposit
C3: Table name | D3: Action | E3: Table name | F3: Action | G3: Table name | H3: Action | I3: Table name | J3: Action
A4: Deposit money for deposit account (current, saving, fixed deposit) | B4: Deposit account - Status: Normal (if prevoius status is New/ Dormant) - Increase Current balance, Available balance - Increase Deposit Amount, Week Credit, Month Credit, Quarter Credit, Semi - Annual Credit and Year Credit - BeginOfTenor = Working, EndOfTenor = Working date + tenor - LastChangeDormantToNormalDate (if previous status is Dormant) Deposit by cash - Increase Customer deposit, Total In, Closing balance of Cash flow Deposit by deposit - Decrease Current balance, Available balance - Increase Withdraw Amount, Week Debit, Month Debit, Quarter Debit, Semi - Annual Debit and Year Debit Deposit by GL - Decrease GL Balance | C4: GLEntries | D4: Insert new row | E4: TransactionJournalDone | F4: Insert new row | G4: CashList | H4: - CurrencyCode already existed: Update old row (update CurrentBalance) - CurrencyCode does not exist: Insert new row | I4: DepositAccount | J4: Update old row - DepositStatus (if prevoius status is New/ Dormant) - Psts - CurrentBalance, DepositAmount, WeekCredit, MonthCredit, QuarterCredit, SemiAnnualCredit, YearCredit - LastTransactionDate, UpdatedOnUtc - BeginOfTenor, EndOfTenor (if deposit type is Fixed Deposit) - LastChangeDormantToNormalDate (if previous status is Dormant) Update old row (if deposit by deposit) - Psts - CurrentBalance, WithdrawAmount, WeekDebit, MonthDebit, QuarterDebit, SemiAnnualDebit, YearDebit - LastTransactionDate, UpdatedOnUtc
C5: AccountBalance | D5: Update old row (update Balance) | E5: Transaction | F5: Insert new row | G5: CashStatement | H5: - CashierCode, CurrencyCode, CashType and ValueDate already existed: Update old row (update CashAmount) - CashierCode, CurrencyCode, CashType and ValueDate do not exist: Insert new row | I5: DepositStatement | J5: Insert new row
C6: AccountStatement | D6: Insert new row | E6: TransactionDetail | F6: Insert new row | G6: CashTransaction | H6: Insert new row | I6: DepositHistory | J6: Insert new row
C7: Transaction | D7: Insert new row | G7: GLEntries | H7: Insert new row | I7: DepositAccountTrans | J7: Insert new row
C8: TransactionDetail | D8: Insert new row | G8: Transaction | H8: Insert new row | I8: GLEntries | J8: Insert new row
G9: TransactionDetail | H9: Insert new row | I9: Transaction | J9: Insert new row
I10: TransactionDetail | J10: Insert new row
A11: Withdraw money for deposit account (current, saving) | B11: Deposit account - Decrease Current balance, Available balance - Increase Withdraw Amount, Week Debit, Month Debit, Quarter Debit, Semi - Annual Debit and Year Debit Withdraw by cash - Increase Customer withdrawal, Total Out, decrease Closing balance of Cash flow Withdraw by deposit - Increase Current balance, Available balance - Increase Deposit Amount, Week Credit, Month Credit, Quarter Credit, Semi - Annual Credit and Year Credit Withdraw by GL - Increase GL Balance | C11: GLEntries | D11: Insert new row | E11: TransactionJournalDone | F11: Insert new row | G11: CashList | H11: Update old row (update CurrentBalance) | I11: DepositAccount | J11: Update old row - DepositStatus (if prevoius status is New) - Psts - CurrentBalance, WithdrawAmount, WeekDebit, MonthDebit, QuarterDebit, SemiAnnualDebit, YearDebit - LastTransactionDate, UpdatedOnUtc - LastChangeDormantToNormalDate (if previous status is Dormant) Update old row (if withdraw by deposit) - DepositStatus (if prevoius status is New) - Psts - CurrentBalance, DepositAmount, WeekCredit, MonthCredit, QuarterCredit, SemiAnnualCredit, YearCredit - LastTransactionDate, UpdatedOnUtc
C12: AccountStatement | D12: Insert new row | E12: Transaction | F12: Insert new row | G12: CashStatement | H12: - CashierCode, CurrencyCode, CashType and ValueDate already existed: Update old row (update CashAmount) - CashierCode, CurrencyCode, CashType and ValueDate do not exist: Insert new row | I12: DepositStatement | J12: Insert new row
C13: Transaction | D13: Insert new row | E13: TransactionDetail | F13: Insert new row | G13: CashTransaction | H13: Insert new row | I13: DepositHistory | J13: Insert new row
C14: TransactionDetail | D14: Insert new row | G14: GLEntries | H14: Insert new row | I14: DepositAccountTrans | J14: Insert new row
G15: Transaction | H15: Insert new row | I15: GLEntries | J15: Insert new row
G16: TransactionDetail | H16: Insert new row | I16: Transaction | J16: Insert new row
I17: TransactionDetail | J17: Insert new row
A18: Deposit money for prepaid fixed deposit | B18: Fixed deposit account - Status: Normal (if prevoius status is New) - Increase Current balance, Available balance - Increase Deposit Amount, Week Credit, Month Credit, Quarter Credit, Semi - Annual Credit and Year Credit - BeginOfTenor = Working, EndOfTenor = Working date + tenor - Increase Interest prepaid Linkage account - Increase Current balance, Available balance - Increase Deposit Amount, Week Credit, Month Credit, Quarter Credit, Semi - Annual Credit and Year Credit Deposit by cash - Increase Customer deposit, Total In, Closing balance of Cash flow Deposit by deposit - Decrease Current balance, Available balance - Increase Withdraw Amount, Week Debit, Month Debit, Quarter Debit, Semi - Annual Debit and Year Debit | C18: GLEntries | D18: Insert new row | E18: TransactionJournalDone | F18: Insert new row | G18: CashList | H18: - CurrencyCode already existed: Update old row (update CurrentBalance) - CurrencyCode does not exist: Insert new row | I18: DepositAccount | J18: Update old row (Prepaid fixed deposit) - DepositStatus (if prevoius status is New) - Psts - CurrentBalance, DepositAmount, WeekCredit, MonthCredit, QuarterCredit, SemiAnnualCredit, YearCredit - LastTransactionDate, UpdatedOnUtc - BeginOfTenor, EndOfTenor (if deposit type is Fixed Deposit) - LastChangeDormantToNormalDate (if previous status is Dormant) Update old row (linkage account) - Psts - CurrentBalance, DepositAmount, WeekCredit, MonthCredit, QuarterCredit, SemiAnnualCredit, YearCredit - LastTransactionDate, UpdatedOnUtc Update old row (if deposit by deposit) - Psts - CurrentBalance, WithdrawAmount, WeekDebit, MonthDebit, QuarterDebit, SemiAnnualDebit, YearDebit - LastTransactionDate, UpdatedOnUtc
C19: AccountBalance | D19: Update old row (update Balance) | E19: Transaction | F19: Insert new row | G19: CashStatement | H19: Insert new row | I19: IFCBalance | J19: Update old row (update PrepaidAmount)
C20: AccountStatement | D20: Insert new row | E20: TransactionDetail | F20: Insert new row | G20: CashTransaction | H20: Insert new row | I20: IFCBalanceDetail | J20: Insert new row
C21: Transaction | D21: Insert new row | G21: GLEntries | H21: Insert new row | I21: DepositStatement | J21: Insert new row
C22: TransactionDetail | D22: Insert new row | G22: Transaction | H22: Insert new row | I22: DepositHistory | J22: Insert new row
G23: TransactionDetail | H23: Insert new row | I23: DepositAccountTrans | J23: Insert new row
I24: DepositIFCBalanceTrans | J24: Insert new row
I25: GLEntries | J25: Insert new row
I26: Transaction | J26: Insert new row
I27: TransactionDetail | J27: Insert new row
A28: Denomination | G28: DenominationBalance | H28: - CurrencyId, FaceValue, BranchCode and CashierCode already existed: Update old row (update Quantity, Amount) - CurrencyId, FaceValue, BranchCode and CashierCode does not exist: Insert new row
G29: DenominationStatement | H29: Insert new row
G30: DenominationTransaction | H30: Insert new row
