Workbook
Name Pass: '[1]Test Case_ILC'!$H$13

Sheet Version
A4: CBS-SHWE_FO_STOCK
D6: Version: 1.0
A7: Version history
A8: Version | B8: Maker | C8: Revision Date | D8: Checker | E8: Approval Date | F8: Document Changes
A9: 1 | B9: VyHNT | C9: 45635 | D9: NhiDY | F9: Create test case

Sheet Summary
B2: Release test case
B3: Date
B4: Time
B5: Total | C5: ='Scenario Test'!J29 -> 172
B7: Execute test 1st time
B8: Date Status
B9: Pass | C9: =COUNTIFS(TestCase!$G:$G,$B$9,TestCase!$J:$J,C8) -> 0 | D9: =COUNTIFS(TestCase!$G:$G,$B$9,TestCase!$J:$J,D8) -> 0 | E9: =COUNTIFS(TestCase!$G:$G,$B$9,TestCase!$J:$J,E8) -> 0 | F9: =COUNTIFS(TestCase!$G:$G,$B$9,TestCase!$J:$J,F8) -> 0
B10: Fail | C10: =COUNTIFS(TestCase!$G:$G,$B$10,TestCase!$J:$J,C8) -> 0 | D10: =COUNTIFS(TestCase!$G:$G,$B$10,TestCase!$J:$J,D8) -> 0 | E10: =COUNTIFS(TestCase!$G:$G,$B$10,TestCase!$J:$J,E8) -> 0 | F10: =COUNTIFS(TestCase!$G:$G,$B$10,TestCase!$J:$J,F8) -> 0
B11: Block | C11: =COUNTIFS(TestCase!$G:$G,$B$11,TestCase!$J:$J,C8) -> 0 | D11: =COUNTIFS(TestCase!$G:$G,$B$11,TestCase!$J:$J,D8) -> 0 | E11: =COUNTIFS(TestCase!$G:$G,$B$11,TestCase!$J:$J,E8) -> 0 | F11: =COUNTIFS(TestCase!$G:$G,$B$11,TestCase!$J:$J,F8) -> 0
B12: Pending | C12: =COUNTIFS(TestCase!$G:$G,$B$12,TestCase!$K:$K,C8) -> 0 | D12: =COUNTIFS(TestCase!$G:$G,$B$12,TestCase!$K:$K,D8) -> 0 | E12: =COUNTIFS(TestCase!$G:$G,$B$12,TestCase!$K:$K,E8) -> 0 | F12: =COUNTIFS(TestCase!$G:$G,$B$12,TestCase!$K:$K,F8) -> 0
B13: Not Completed | C13: =COUNTIFS(TestCase!$G:$G,$B$13,TestCase!$K:$K,C8) -> 0 | D13: =COUNTIFS(TestCase!$G:$G,$B$13,TestCase!$K:$K,D8) -> 0 | E13: =COUNTIFS(TestCase!$G:$G,$B$13,TestCase!$K:$K,E8) -> 0 | F13: =COUNTIFS(TestCase!$G:$G,$B$13,TestCase!$K:$K,F8) -> 0
B14: Actual execution | C14: =SUM(C9:C13) -> 0 | D14: =SUM(D9:D13) -> 0 | E14: =SUM(E9:E13) -> 0 | F14: =SUM(F9:F13) -> 0
B15: Not yet execution | C15: =$C$5-C14 -> 172 | D15: =C15-D14 -> 172 | E15: =D15-E14 -> 172 | F15: =E15-F14 -> 172
B17: Execute test 2nd time
B18: Date Status
B19: Pass | C19: =COUNTIFS(TestCase!$G:$G,$B$19,TestCase!$K:$K,C18) -> 0 | D19: =COUNTIFS(TestCase!$G:$G,$B$19,TestCase!$K:$K,D18) -> 0 | E19: =COUNTIFS(TestCase!$G:$G,$B$19,TestCase!$K:$K,E18) -> 0 | F19: =COUNTIFS(TestCase!$G:$G,$B$19,TestCase!$K:$K,F18) -> 0
B20: Fail | C20: =COUNTIFS(TestCase!$G:$G,$B$20,TestCase!$K:$K,C18) -> 0 | D20: =COUNTIFS(TestCase!$G:$G,$B$20,TestCase!$K:$K,D18) -> 0 | E20: =COUNTIFS(TestCase!$G:$G,$B$20,TestCase!$K:$K,E18) -> 0 | F20: =COUNTIFS(TestCase!$G:$G,$B$20,TestCase!$K:$K,F18) -> 0
B21: Block | C21: =COUNTIFS(TestCase!$G:$G,$B$21,TestCase!$K:$K,C18) -> 0 | D21: =COUNTIFS(TestCase!$G:$G,$B$21,TestCase!$K:$K,D18) -> 0 | E21: =COUNTIFS(TestCase!$G:$G,$B$21,TestCase!$K:$K,E18) -> 0 | F21: =COUNTIFS(TestCase!$G:$G,$B$21,TestCase!$K:$K,F18) -> 0
B22: Pending | C22: =COUNTIFS(TestCase!$G:$G,$B$22,TestCase!$K:$K,C18) -> 0 | D22: =COUNTIFS(TestCase!$G:$G,$B$22,TestCase!$K:$K,D18) -> 0 | E22: =COUNTIFS(TestCase!$G:$G,$B$22,TestCase!$K:$K,E18) -> 0 | F22: =COUNTIFS(TestCase!$G:$G,$B$22,TestCase!$K:$K,F18) -> 0
B23: Not Completed | C23: =COUNTIFS(TestCase!$G:$G,$B$23,TestCase!$K:$K,C18) -> 0 | D23: =COUNTIFS(TestCase!$G:$G,$B$23,TestCase!$K:$K,D18) -> 0 | E23: =COUNTIFS(TestCase!$G:$G,$B$23,TestCase!$K:$K,E18) -> 0 | F23: =COUNTIFS(TestCase!$G:$G,$B$23,TestCase!$K:$K,F18) -> 0
B24: Actual execution | C24: =SUM(C19:C23) -> 0 | D24: =SUM(D19:D23) -> 0 | E24: =SUM(E19:E23) -> 0 | F24: =SUM(F19:F23) -> 0
B25: Not yet execution | C25: =$C$5-C24 -> 172 | D25: =C25-D24 -> 172 | E25: =D25-E24 -> 172 | F25: =E25-F24 -> 172
B27: Percent execute test case
B28: Percent pass | C28: ='Scenario Test'!K29 -> 0
B29: Percent fail | C29: ='Scenario Test'!L29 -> 0
B30: Percent block | C30: ='Scenario Test'!N29 -> 0
B31: Percent pending | C31: ='Scenario Test'!O29 -> 0
B32: Percent not completed | C32: ='Scenario Test'!P29 -> 0
B33: Percent not run | C33: ='Scenario Test'!M29 -> 1
B35: Execute test case
B36: Pass | C36: ='Scenario Test'!C29 -> 0
B37: Fail | C37: ='Scenario Test'!D29 -> 0
B38: Block | C38: ='Scenario Test'!F29 -> 0
B39: Pending | C39: ='Scenario Test'!G29 -> 0
B40: Not Completed | C40: ='Scenario Test'!H29 -> 0
B41: Not run | C41: ='Scenario Test'!E29 -> 172

Sheet Scenario Test
A2: SUMMARY
A4: Scenario ID | B4: Scenario name | C4: Pass | D4: Fail | E4: + | F4: Block | G4: Pending | H4: Not Completed | I4: - | J4: Total | K4: Percent pass | L4: Percent fail | M4: Percent not run | N4: Percent block | O4: Percent pending | P4: Percent not completed | Q4: Remark
A5: Stock transaction
A6: DPT_SRG | B6: DPT_SRG: 11830: Stock Registration | C6: =COUNTIFS(TestCase!$A:$A,A6,TestCase!$G:$G,$C$4) -> 0 | D6: =COUNTIFS(TestCase!$A:$A,A6,TestCase!$G:$G,$D$4) -> 0 | E6: =COUNTIFS(TestCase!$A:$A,A6,TestCase!$G:$G,$E$4) -> 0 | F6: =COUNTIFS(TestCase!$A:$A,A6,TestCase!$G:$G,$F$4) -> 0 | G6: =COUNTIFS(TestCase!$A:$A,A6,TestCase!$G:$G,$G$4) -> 0 | H6: =COUNTIFS(TestCase!$A:$A,A6,TestCase!$G:$G,$H$4) -> 0 | I6: =COUNTIFS(TestCase!$A:$A,A6,TestCase!$G:$G,$I$4) -> 0 | J6: =SUM(C6:H6) -> 0 | K6: =IFERROR(ROUND(C6/J6,4),0) -> 0 | L6: =IFERROR(ROUND(D6/J6,4),0) -> 0 | M6: =IFERROR(ROUND(E6/J6,4),0) -> 0 | N6: =IFERROR(ROUND(F6/J6,4),0) -> 0 | O6: =IFERROR(ROUND(G6/J6,4),0) -> 0 | P6: =IFERROR(ROUND(H6/$J$6,4),0) -> 0
A7: DPT_SAB | B7: DPT_SAB: 11831: Stock assigned to branch | C7: =COUNTIFS(TestCase!$A:$A,A7,TestCase!$G:$G,$C$4) -> 0 | D7: =COUNTIFS(TestCase!$A:$A,A7,TestCase!$G:$G,$D$4) -> 0 | E7: =COUNTIFS(TestCase!$A:$A,A7,TestCase!$G:$G,$E$4) -> 0 | F7: =COUNTIFS(TestCase!$A:$A,A7,TestCase!$G:$G,$F$4) -> 0 | G7: =COUNTIFS(TestCase!$A:$A,A7,TestCase!$G:$G,$G$4) -> 0 | H7: =COUNTIFS(TestCase!$A:$A,A7,TestCase!$G:$G,$H$4) -> 0 | I7: =COUNTIFS(TestCase!$A:$A,A7,TestCase!$G:$G,$I$4) -> 0 | J7: =SUM(C7:H7) -> 0 | K7: =IFERROR(ROUND(C7/J7,4),0) -> 0 | L7: =IFERROR(ROUND(D7/J7,4),0) -> 0 | M7: =IFERROR(ROUND(E7/J7,4),0) -> 0 | N7: =IFERROR(ROUND(F7/J7,4),0) -> 0 | O7: =IFERROR(ROUND(G7/J7,4),0) -> 0 | P7: =IFERROR(ROUND(H7/$J$6,4),0) -> 0
A8: DPT_SAT | B8: DPT_SAT: 11832: Stock assigned to teller | C8: =COUNTIFS(TestCase!$A:$A,A8,TestCase!$G:$G,$C$4) -> 0 | D8: =COUNTIFS(TestCase!$A:$A,A8,TestCase!$G:$G,$D$4) -> 0 | E8: =COUNTIFS(TestCase!$A:$A,A8,TestCase!$G:$G,$E$4) -> 0 | F8: =COUNTIFS(TestCase!$A:$A,A8,TestCase!$G:$G,$F$4) -> 0 | G8: =COUNTIFS(TestCase!$A:$A,A8,TestCase!$G:$G,$G$4) -> 0 | H8: =COUNTIFS(TestCase!$A:$A,A8,TestCase!$G:$G,$H$4) -> 0 | I8: =COUNTIFS(TestCase!$A:$A,A8,TestCase!$G:$G,$I$4) -> 0 | J8: =SUM(C8:H8) -> 0 | K8: =IFERROR(ROUND(C8/J8,4),0) -> 0 | L8: =IFERROR(ROUND(D8/J8,4),0) -> 0 | M8: =IFERROR(ROUND(E8/J8,4),0) -> 0 | N8: =IFERROR(ROUND(F8/J8,4),0) -> 0 | O8: =IFERROR(ROUND(G8/J8,4),0) -> 0 | P8: =IFERROR(ROUND(H8/$J$6,4),0) -> 0
A9: DPT_CCR | B9: DPT_CCR: 11834: Stock confirm received (by branch or teller) | C9: =COUNTIFS(TestCase!$A:$A,A9,TestCase!$G:$G,$C$4) -> 0 | D9: =COUNTIFS(TestCase!$A:$A,A9,TestCase!$G:$G,$D$4) -> 0 | E9: =COUNTIFS(TestCase!$A:$A,A9,TestCase!$G:$G,$E$4) -> 0 | F9: =COUNTIFS(TestCase!$A:$A,A9,TestCase!$G:$G,$F$4) -> 0 | G9: =COUNTIFS(TestCase!$A:$A,A9,TestCase!$G:$G,$G$4) -> 0 | H9: =COUNTIFS(TestCase!$A:$A,A9,TestCase!$G:$G,$H$4) -> 0 | I9: =COUNTIFS(TestCase!$A:$A,A9,TestCase!$G:$G,$I$4) -> 0 | J9: =SUM(C9:H9) -> 0 | K9: =IFERROR(ROUND(C9/J9,4),0) -> 0 | L9: =IFERROR(ROUND(D9/J9,4),0) -> 0 | M9: =IFERROR(ROUND(E9/J9,4),0) -> 0 | N9: =IFERROR(ROUND(F9/J9,4),0) -> 0 | O9: =IFERROR(ROUND(G9/J9,4),0) -> 0 | P9: =IFERROR(ROUND(H9/$J$6,4),0) -> 0
A10: DPT_SRA | B10: DPT_SRA: 11835: Reject assigned stock (by branch or telller) | C10: =COUNTIFS(TestCase!$A:$A,A10,TestCase!$G:$G,$C$4) -> 0 | D10: =COUNTIFS(TestCase!$A:$A,A10,TestCase!$G:$G,$D$4) -> 0 | E10: =COUNTIFS(TestCase!$A:$A,A10,TestCase!$G:$G,$E$4) -> 0 | F10: =COUNTIFS(TestCase!$A:$A,A10,TestCase!$G:$G,$F$4) -> 0 | G10: =COUNTIFS(TestCase!$A:$A,A10,TestCase!$G:$G,$G$4) -> 0 | H10: =COUNTIFS(TestCase!$A:$A,A10,TestCase!$G:$G,$H$4) -> 0 | I10: =COUNTIFS(TestCase!$A:$A,A10,TestCase!$G:$G,$I$4) -> 0 | J10: =SUM(C10:H10) -> 0 | K10: =IFERROR(ROUND(C10/J10,4),0) -> 0 | L10: =IFERROR(ROUND(D10/J10,4),0) -> 0 | M10: =IFERROR(ROUND(E10/J10,4),0) -> 0 | N10: =IFERROR(ROUND(F10/J10,4),0) -> 0 | O10: =IFERROR(ROUND(G10/J10,4),0) -> 0 | P10: =IFERROR(ROUND(H10/$J$6,4),0) -> 0
A11: DPT_CRT | B11: DPT_CRT: 11833: Stock return (by branch or teller) | C11: =COUNTIFS(TestCase!$A:$A,A11,TestCase!$G:$G,$C$4) -> 0 | D11: =COUNTIFS(TestCase!$A:$A,A11,TestCase!$G:$G,$D$4) -> 0 | E11: =COUNTIFS(TestCase!$A:$A,A11,TestCase!$G:$G,$E$4) -> 0 | F11: =COUNTIFS(TestCase!$A:$A,A11,TestCase!$G:$G,$F$4) -> 0 | G11: =COUNTIFS(TestCase!$A:$A,A11,TestCase!$G:$G,$G$4) -> 0 | H11: =COUNTIFS(TestCase!$A:$A,A11,TestCase!$G:$G,$H$4) -> 0 | I11: =COUNTIFS(TestCase!$A:$A,A11,TestCase!$G:$G,$I$4) -> 0 | J11: =SUM(C11:H11) -> 0 | K11: =IFERROR(ROUND(C11/J11,4),0) -> 0 | L11: =IFERROR(ROUND(D11/J11,4),0) -> 0 | M11: =IFERROR(ROUND(E11/J11,4),0) -> 0 | N11: =IFERROR(ROUND(F11/J11,4),0) -> 0 | O11: =IFERROR(ROUND(G11/J11,4),0) -> 0 | P11: =IFERROR(ROUND(H11/$J$6,4),0) -> 0
A12: DPT_CIS | B12: DPT_CIS: 11801: Cheque book issued | C12: =COUNTIFS(TestCase!$A:$A,A12,TestCase!$G:$G,$C$4) -> 0 | D12: =COUNTIFS(TestCase!$A:$A,A12,TestCase!$G:$G,$D$4) -> 0 | E12: =COUNTIFS(TestCase!$A:$A,A12,TestCase!$G:$G,$E$4) -> 38 | F12: =COUNTIFS(TestCase!$A:$A,A12,TestCase!$G:$G,$F$4) -> 0 | G12: =COUNTIFS(TestCase!$A:$A,A12,TestCase!$G:$G,$G$4) -> 0 | H12: =COUNTIFS(TestCase!$A:$A,A12,TestCase!$G:$G,$H$4) -> 0 | I12: =COUNTIFS(TestCase!$A:$A,A12,TestCase!$G:$G,$I$4) -> 0 | J12: =SUM(C12:H12) -> 38 | K12: =IFERROR(ROUND(C12/J12,4),0) -> 0 | L12: =IFERROR(ROUND(D12/J12,4),0) -> 0 | M12: =IFERROR(ROUND(E12/J12,4),0) -> 1 | N12: =IFERROR(ROUND(F12/J12,4),0) -> 0 | O12: =IFERROR(ROUND(G12/J12,4),0) -> 0 | P12: =IFERROR(ROUND(H12/$J$6,4),0) -> 0
A13: DPT_SBI | B13: DPT_SBI: 11802: Deposit saving book issued | C13: =COUNTIFS(TestCase!$A:$A,A13,TestCase!$G:$G,$C$4) -> 0 | D13: =COUNTIFS(TestCase!$A:$A,A13,TestCase!$G:$G,$D$4) -> 0 | E13: =COUNTIFS(TestCase!$A:$A,A13,TestCase!$G:$G,$E$4) -> 30 | F13: =COUNTIFS(TestCase!$A:$A,A13,TestCase!$G:$G,$F$4) -> 0 | G13: =COUNTIFS(TestCase!$A:$A,A13,TestCase!$G:$G,$G$4) -> 0 | H13: =COUNTIFS(TestCase!$A:$A,A13,TestCase!$G:$G,$H$4) -> 0 | I13: =COUNTIFS(TestCase!$A:$A,A13,TestCase!$G:$G,$I$4) -> 0 | J13: =SUM(C13:H13) -> 30 | K13: =IFERROR(ROUND(C13/J13,4),0) -> 0 | L13: =IFERROR(ROUND(D13/J13,4),0) -> 0 | M13: =IFERROR(ROUND(E13/J13,4),0) -> 1 | N13: =IFERROR(ROUND(F13/J13,4),0) -> 0 | O13: =IFERROR(ROUND(G13/J13,4),0) -> 0 | P13: =IFERROR(ROUND(H13/$J$6,4),0) -> 0
A14: DPT_FBI | B14: DPT_FBI: 11804: Fixed deposit book issue | C14: =COUNTIFS(TestCase!$A:$A,A14,TestCase!$G:$G,$C$4) -> 0 | D14: =COUNTIFS(TestCase!$A:$A,A14,TestCase!$G:$G,$D$4) -> 0 | E14: =COUNTIFS(TestCase!$A:$A,A14,TestCase!$G:$G,$E$4) -> 29 | F14: =COUNTIFS(TestCase!$A:$A,A14,TestCase!$G:$G,$F$4) -> 0 | G14: =COUNTIFS(TestCase!$A:$A,A14,TestCase!$G:$G,$G$4) -> 0 | H14: =COUNTIFS(TestCase!$A:$A,A14,TestCase!$G:$G,$H$4) -> 0 | I14: =COUNTIFS(TestCase!$A:$A,A14,TestCase!$G:$G,$I$4) -> 0 | J14: =SUM(C14:H14) -> 29 | K14: =IFERROR(ROUND(C14/J14,4),0) -> 0 | L14: =IFERROR(ROUND(D14/J14,4),0) -> 0 | M14: =IFERROR(ROUND(E14/J14,4),0) -> 1 | N14: =IFERROR(ROUND(F14/J14,4),0) -> 0 | O14: =IFERROR(ROUND(G14/J14,4),0) -> 0 | P14: =IFERROR(ROUND(H14/$J$6,4),0) -> 0
A15: DPT_CER | B15: DPT_CER: 11803: Fixed deposit receipt issue | C15: =COUNTIFS(TestCase!$A:$A,A15,TestCase!$G:$G,$C$4) -> 0 | D15: =COUNTIFS(TestCase!$A:$A,A15,TestCase!$G:$G,$D$4) -> 0 | E15: =COUNTIFS(TestCase!$A:$A,A15,TestCase!$G:$G,$E$4) -> 30 | F15: =COUNTIFS(TestCase!$A:$A,A15,TestCase!$G:$G,$F$4) -> 0 | G15: =COUNTIFS(TestCase!$A:$A,A15,TestCase!$G:$G,$G$4) -> 0 | H15: =COUNTIFS(TestCase!$A:$A,A15,TestCase!$G:$G,$H$4) -> 0 | I15: =COUNTIFS(TestCase!$A:$A,A15,TestCase!$G:$G,$I$4) -> 0 | J15: =SUM(C15:H15) -> 30 | K15: =IFERROR(ROUND(C15/J15,4),0) -> 0 | L15: =IFERROR(ROUND(D15/J15,4),0) -> 0 | M15: =IFERROR(ROUND(E15/J15,4),0) -> 1 | N15: =IFERROR(ROUND(F15/J15,4),0) -> 0 | O15: =IFERROR(ROUND(G15/J15,4),0) -> 0 | P15: =IFERROR(ROUND(H15/$J$6,4),0) -> 0
A16: DPT_CEI | B16: DPT_CEI: 11850: Issued hold balance for cheque | C16: =COUNTIFS(TestCase!$A:$A,A16,TestCase!$G:$G,$C$4) -> 0 | D16: =COUNTIFS(TestCase!$A:$A,A16,TestCase!$G:$G,$D$4) -> 0 | E16: =COUNTIFS(TestCase!$A:$A,A16,TestCase!$G:$G,$E$4) -> 0 | F16: =COUNTIFS(TestCase!$A:$A,A16,TestCase!$G:$G,$F$4) -> 0 | G16: =COUNTIFS(TestCase!$A:$A,A16,TestCase!$G:$G,$G$4) -> 0 | H16: =COUNTIFS(TestCase!$A:$A,A16,TestCase!$G:$G,$H$4) -> 0 | I16: =COUNTIFS(TestCase!$A:$A,A16,TestCase!$G:$G,$I$4) -> 0 | J16: =SUM(C16:H16) -> 0 | K16: =IFERROR(ROUND(C16/J16,4),0) -> 0 | L16: =IFERROR(ROUND(D16/J16,4),0) -> 0 | M16: =IFERROR(ROUND(E16/J16,4),0) -> 0 | N16: =IFERROR(ROUND(F16/J16,4),0) -> 0 | O16: =IFERROR(ROUND(G16/J16,4),0) -> 0 | P16: =IFERROR(ROUND(H16/$J$6,4),0) -> 0
A17: DPT_REC | B17: DPT_REC: 11852: Release hold balance for cheque | C17: =COUNTIFS(TestCase!$A:$A,A17,TestCase!$G:$G,$C$4) -> 0 | D17: =COUNTIFS(TestCase!$A:$A,A17,TestCase!$G:$G,$D$4) -> 0 | E17: =COUNTIFS(TestCase!$A:$A,A17,TestCase!$G:$G,$E$4) -> 0 | F17: =COUNTIFS(TestCase!$A:$A,A17,TestCase!$G:$G,$F$4) -> 0 | G17: =COUNTIFS(TestCase!$A:$A,A17,TestCase!$G:$G,$G$4) -> 0 | H17: =COUNTIFS(TestCase!$A:$A,A17,TestCase!$G:$G,$H$4) -> 0 | I17: =COUNTIFS(TestCase!$A:$A,A17,TestCase!$G:$G,$I$4) -> 0 | J17: =SUM(C17:H17) -> 0 | K17: =IFERROR(ROUND(C17/J17,4),0) -> 0 | L17: =IFERROR(ROUND(D17/J17,4),0) -> 0 | M17: =IFERROR(ROUND(E17/J17,4),0) -> 0 | N17: =IFERROR(ROUND(F17/J17,4),0) -> 0 | O17: =IFERROR(ROUND(G17/J17,4),0) -> 0 | P17: =IFERROR(ROUND(H17/$J$6,4),0) -> 0
... A28: DPT_RPO | B28: DPT_RPO: 11818: Payment order return | C28: =COUNTIFS(TestCase!$A:$A,A28,TestCase!$G:$G,$C$4) -> 0 | D28: =COUNTIFS(TestCase!$A:$A,A28,TestCase!$G:$G,$D$4) -> 0 | E28: =COUNTIFS(TestCase!$A:$A,A28,TestCase!$G:$G,$E$4) -> 0 | F28: =COUNTIFS(TestCase!$A:$A,A28,TestCase!$G:$G,$F$4) -> 0 | G28: =COUNTIFS(TestCase!$A:$A,A28,TestCase!$G:$G,$G$4) -> 0 | H28: =COUNTIFS(TestCase!$A:$A,A28,TestCase!$G:$G,$H$4) -> 0 | I28: =COUNTIFS(TestCase!$A:$A,A28,TestCase!$G:$G,$I$4) -> 0 | J28: =SUM(C28:H28) -> 0 | K28: =IFERROR(ROUND(C28/J28,4),0) -> 0 | L28: =IFERROR(ROUND(D28/J28,4),0) -> 0 | M28: =IFERROR(ROUND(E28/J28,4),0) -> 0 | N28: =IFERROR(ROUND(F28/J28,4),0) -> 0 | O28: =IFERROR(ROUND(G28/J28,4),0) -> 0 | P28: =IFERROR(ROUND(H28/$J$6,4),0) -> 0
A29: Total | C29: =SUM(C6:C28) -> 0 | D29: =SUM(D6:D28) -> 0 | E29: =SUM(E6:E28) -> 172 | F29: =SUM(F6:F28) -> 0 | G29: =SUM(G6:G28) -> 0 | H29: =SUM(H6:H28) -> 0 | I29: =SUM(I6:I28) -> 0 | J29: =SUM(J6:J28) -> 172 | K29: =IFERROR(100%-SUM(L29:P29),0) -> 0 | L29: =IFERROR(ROUND(D29/$J$29,4),0) -> 0 | M29: =IFERROR(ROUND(E29/$J$29,4),0) -> 1 | N29: =IFERROR(ROUND(F29/$J$29,4),0) -> 0 | O29: =IFERROR(ROUND(G29/$J$29,4),0) -> 0 | P29: =IFERROR(ROUND(H29/$J$29,4),0) -> 0
A31: Remark: Status of Test Scenario on section “Overall Status”:
A32: - Passed = Test Scenario has been tested as planned and application works as expected result.
A33: - Failed = Test Scenario has been tested as planned but application does not work as expected.
A34: - Blocked = Test Scenario could not be tested as planned because there is an outstanding defect in related function area.
A35: - Not Completed = Test Scenario has been tested as planned but not yet finished due to awaiting test result (ex: require EOD batch).
A36: - No Run (+) = Test Scenario has not been tested as planned.
A37: - Pending = Test Scenario will be tested after confirming about the business.
A38: - Cancel (-) = Test Scenario could not be tested because of wrong condition, not suitable with the environment.

Sheet TestCase
A2: TEST CASES
A3: Environment:
A5: Scenario ID | B5: Scenario name | C5: Test case ID | D5: Test condition ID | E5: Condition | F5: Expected Result | G5: Result | H5: Comments | I5: Create date | J5: Test lần 1 | K5: Test lần 2 | L5: Test lần 3 | M5: Test lần 4 | N5: Executor | O5: Creator (Editor) | P5: Update date
A6: ='Scenario Test'!$A$12 -> DPT_CIS | B6: =VLOOKUP(TestCase!A6,'Scenario Test'!$A$4:$B$125,2,0) -> DPT_CIS: 11801: Cheque book issued
A7: ='Scenario Test'!$A$12 -> DPT_CIS | B7: =VLOOKUP(TestCase!A7,'Scenario Test'!$A$4:$B$125,2,0) -> DPT_CIS: 11801: Cheque book issued | C7: DPT_CIS_001 | E7: Books exist: - Stock type: Cheque - Book status: Assigned to teller - Confirm status: Confirmed - Status of stock leaves: Normal - Belongs to teller does this transaction Deposit account: - Deposit type: Current - Deposit status: New/ Normal/ Dormant Issued 1 book 1. Open "Cheque book issued" screen 2. Input Account number 3. Input From serial 4. Input To serial 5. Click Accept | F7: Transaction successfully Print voucher of stock Update stock: All leaves of books have status "Unpaid" | G7: + | I7: 45630 | O7: VyHNT
A8: ='Scenario Test'!$A$12 -> DPT_CIS | B8: =VLOOKUP(TestCase!A8,'Scenario Test'!$A$4:$B$125,2,0) -> DPT_CIS: 11801: Cheque book issued | C8: DPT_CIS_002 | E8: Books exist: - Stock type: Cheque - Book status: Assigned to teller - Confirm status: Confirmed - Status of stock leaves: Normal - Belongs to teller does this transaction Deposit account: - Deposit type: Current - Deposit status: New/ Normal/ Dormant Issued many books 1. Open "Cheque book issued" screen 2. Input Account number 3. Input From serial 4. Input To serial 5. Click Accept | F8: Transaction successfully Print voucher of stock Update stock: All leaves of books have status "Unpaid" | G8: + | I8: 45630 | O8: VyHNT
A9: ='Scenario Test'!$A$12 -> DPT_CIS | B9: =VLOOKUP(TestCase!A9,'Scenario Test'!$A$4:$B$125,2,0) -> DPT_CIS: 11801: Cheque book issued | C9: DPT_CIS_003 | E9: Books exist: - Stock type: Cheque - Book status: Assigned to teller - Confirm status: Confirmed - Status of stock leaves: Normal - Belongs to teller does this transaction Deposit account: - Deposit type: Current - Deposit status: New/ Normal/ Dormant Fee collect method is Cash - User has right to do transaction related to cash Issued 1 book 1. Open "Cheque book issued" screen 2. Input Account number 3. Input From serial 4. Input To serial 5. Choose Fee collect method 6. Add fee 7. Click Accept | F9: Transaction successfully Print voucher of stock Update stock: All leaves of books have status "Unpaid" | G9: + | I9: 45630 | O9: VyHNT
A10: ='Scenario Test'!$A$12 -> DPT_CIS | B10: =VLOOKUP(TestCase!A10,'Scenario Test'!$A$4:$B$125,2,0) -> DPT_CIS: 11801: Cheque book issued | C10: DPT_CIS_004 | E10: Books exist: - Stock type: Cheque - Book status: Assigned to teller - Confirm status: Confirmed - Status of stock leaves: Normal - Belongs to teller does this transaction Deposit account: - Deposit type: Current - Deposit status: New/ Normal/ Dormant Fee collect method is Deposit - Deposit type: Current - Deposit status: Normal - Available balance >= Total fee amount - Same currency with current account Issued 1 book 1. Open "Cheque book issued" screen 2. Input Account number 3. Input From serial 4. Input To serial 5. Choose Fee collect method 6. Add fee 7. Click Accept | F10: Transaction successfully Print voucher of stock Update stock: All leaves of books have status "Unpaid" | G10: + | I10: 45630 | O10: VyHNT
A11: ='Scenario Test'!$A$12 -> DPT_CIS | B11: =VLOOKUP(TestCase!A11,'Scenario Test'!$A$4:$B$125,2,0) -> DPT_CIS: 11801: Cheque book issued | C11: DPT_CIS_005 | E11: Books exist: - Stock type: Cheque - Book status: Assigned to teller - Confirm status: Confirmed - Status of stock leaves: Normal - Belongs to teller does this transaction Deposit account: - Deposit type: Current - Deposit status: New/ Normal/ Dormant Fee collect method is Deposit - Deposit type: Saving - Deposit sub type <> Shwe cash call - Deposit status: Normal - Available balance >= Total fee amount - Same currency with current account Issued 1 book 1. Open "Cheque book issued" screen 2. Input Account number 3. Input From serial 4. Input To serial 5. Choose Fee collect method 6. Add fee 7. Click Accept | F11: Transaction successfully Print voucher of stock Update stock: All leaves of books have status "Unpaid" | G11: + | I11: 45630 | O11: VyHNT
A12: ='Scenario Test'!$A$12 -> DPT_CIS | B12: =VLOOKUP(TestCase!A12,'Scenario Test'!$A$4:$B$125,2,0) -> DPT_CIS: 11801: Cheque book issued | C12: DPT_CIS_006 | E12: Books exist: - Stock type: Cheque - Book status: Assigned to teller - Confirm status: Confirmed - Status of stock leaves: Normal - Belongs to teller does this transaction Deposit account: - Deposit type: Current - Deposit status: New/ Normal/ Dormant Fee collect method is Accounting - Posting side: Debit/ Both - Account level: 9 - GL currency = Deposit currency - Account group <> Cash - Direct posting: Yes - Branch account = Branch teller Issued 1 book 1. Open "Cheque book issued" screen 2. Input Account number 3. Input From serial 4. Input To serial 5. Choose Fee collect method 6. Add fee 7. Click Accept | F12: Transaction successfully Print voucher of stock Update stock: All leaves of books have status "Unpaid" | G12: + | I12: 45630 | O12: VyHNT
A13: ='Scenario Test'!$A$12 -> DPT_CIS | B13: =VLOOKUP(TestCase!A13,'Scenario Test'!$A$4:$B$125,2,0) -> DPT_CIS: 11801: Cheque book issued | C13: DPT_CIS_007 | E13: Books exist: - Stock type: Cheque - Book status: Assigned to teller - Confirm status: Confirmed - Status of stock leaves: Normal - Belongs to teller does this transaction Deposit account: - Deposit type: Current - Account status is Normal Fee collect method is Deposit - Deposit type: Current - Deposit status: Normal - Available balance of master < Total fee amount <= Available balance of linkage - Same currency with current account - Has linkage account for fund transfer Linkage account - Deposit type: Saving - Deposit status: Normal - Linkage class: Auto fund transfer Issued 1 book 1. Open "Cheque book issued" screen 2. Input Account number 3. Input From serial 4. Input To serial 5. Choose Fee collect method 6. Add fee 7. Click Accept | F13: Transaction successfully Print voucher of stock Update stock: All leaves of books have status "Unpaid" | G13: + | I13: 45630 | O13: VyHNT
A14: ='Scenario Test'!$A$12 -> DPT_CIS | B14: =VLOOKUP(TestCase!A14,'Scenario Test'!$A$4:$B$125,2,0) -> DPT_CIS: 11801: Cheque book issued | C14: DPT_CIS_008 | E14: Account number is empty | F14: Transaction failed Show error message | G14: + | I14: 45630 | O14: VyHNT
A15: ='Scenario Test'!$A$12 -> DPT_CIS | B15: =VLOOKUP(TestCase!A15,'Scenario Test'!$A$4:$B$125,2,0) -> DPT_CIS: 11801: Cheque book issued | C15: DPT_CIS_009 | E15: Account number does not exist | F15: Transaction failed Show error message | G15: + | I15: 45630 | O15: VyHNT
A16: ='Scenario Test'!$A$12 -> DPT_CIS | B16: =VLOOKUP(TestCase!A16,'Scenario Test'!$A$4:$B$125,2,0) -> DPT_CIS: 11801: Cheque book issued | C16: DPT_CIS_010 | E16: From serial is empty | F16: Transaction failed Show error message | G16: + | I16: 45630 | O16: VyHNT
A17: ='Scenario Test'!$A$12 -> DPT_CIS | B17: =VLOOKUP(TestCase!A17,'Scenario Test'!$A$4:$B$125,2,0) -> DPT_CIS: 11801: Cheque book issued | C17: DPT_CIS_011 | E17: From serial does not exist | F17: Transaction failed Show error message | G17: + | I17: 45630 | O17: VyHNT
A18: ='Scenario Test'!$A$12 -> DPT_CIS | B18: =VLOOKUP(TestCase!A18,'Scenario Test'!$A$4:$B$125,2,0) -> DPT_CIS: 11801: Cheque book issued | C18: DPT_CIS_012 | E18: To serial is empty | F18: Transaction failed Show error message | G18: + | I18: 45630 | O18: VyHNT
... A44: ='Scenario Test'!$A$12 -> DPT_CIS | B44: =VLOOKUP(TestCase!A44,'Scenario Test'!$A$4:$B$125,2,0) -> DPT_CIS: 11801: Cheque book issued | C44: DPT_CIS_038 | E44: Reverse transaction | F44: Transaction successfully | G44: + | I44: 45630 | O44: VyHNT
A45: ='Scenario Test'!$A$13 -> DPT_SBI | B45: =VLOOKUP(TestCase!A45,'Scenario Test'!$A$4:$B$125,2,0) -> DPT_SBI: 11802: Deposit saving book issued
A46: ='Scenario Test'!$A$13 -> DPT_SBI | B46: =VLOOKUP(TestCase!A46,'Scenario Test'!$A$4:$B$125,2,0) -> DPT_SBI: 11802: Deposit saving book issued | C46: DPT_SBI_001 | E46: Books exist - Stock type: Passbook - Book status: Assigned to teller - Confirm status: Confirmed - Status of stock leaves: Normal - Belongs to teller does this transaction Deposit account - Deposit type: Saving - Deposit status: New/ Normal/ Dormant - Have no passbook 1. Open "Deposit savings book issue" screen 2. Input Account number 3. Input Serial no 4. Click Accept | F46: Transaction successfully - Update in stock: + Books have status "Normal". (BookStatus) + Ref account no (RefAccountNo) + Allow print receipt - Update in deposit account: + Passbook number (PassbookOrReceiptNumber) + Passbook status (PassbookOrReceiptStatus) + Deposit status (DepositStatus) + Ref. account No. (Udfield1) | G46: + | I46: 45630 | O46: VyHNT
A47: ='Scenario Test'!$A$13 -> DPT_SBI | B47: =VLOOKUP(TestCase!A47,'Scenario Test'!$A$4:$B$125,2,0) -> DPT_SBI: 11802: Deposit saving book issued | C47: DPT_SBI_002 | E47: Books exist - Stock type: Passbook - Book status: Assigned to teller - Confirm status: Confirmed - Status of stock leaves: Normal - Belongs to teller does this transaction Deposit account - Deposit type: Saving - Deposit status: New/ Normal/ Dormant - Already has passbook with status <> Normal 1. Open "Deposit savings book issue" screen 2. Input Account number 3. Input Serial no 4. Click Accept | F47: Transaction successfully - Update in stock: + Books have status "Normal". (BookStatus) + Ref account no (RefAccountNo) + Allow print receipt - Update in deposit account: + Passbook number (PassbookOrReceiptNumber) + Passbook status (PassbookOrReceiptStatus) + Deposit status (DepositStatus) + Ref. account No. (Udfield1) | G47: + | H47: (vẫn fail đối với stock có status là Stop payment) | I47: 45630 | O47: VyHNT
A48: ='Scenario Test'!$A$13 -> DPT_SBI | B48: =VLOOKUP(TestCase!A48,'Scenario Test'!$A$4:$B$125,2,0) -> DPT_SBI: 11802: Deposit saving book issued | C48: DPT_SBI_003 | E48: Books exist - Stock type: Passbook - Book status: Assigned to teller - Confirm status: Confirmed - Status of stock leaves: Normal - Belongs to teller does this transaction Deposit account - Deposit type: Saving - Deposit status: New/ Normal/ Dormant - Have no passbook Fee collect method is Cash - User has right to do transaction related to cash 1. Open "Deposit savings book issue" screen 2. Input Account number 3. Input Serial no 4. Add fee 5. Click Accept | F48: Transaction successfully - Update in stock: + Books have status "Normal". (BookStatus) + Ref account no (RefAccountNo) + Allow print receipt - Update in deposit account: + Passbook number (PassbookOrReceiptNumber) + Passbook status (PassbookOrReceiptStatus) + Deposit status (DepositStatus) + Ref. account No. (Udfield1) - Update cash flow | G48: + | I48: 45630 | O48: VyHNT
A49: ='Scenario Test'!$A$13 -> DPT_SBI | B49: =VLOOKUP(TestCase!A49,'Scenario Test'!$A$4:$B$125,2,0) -> DPT_SBI: 11802: Deposit saving book issued | C49: DPT_SBI_004 | E49: Books exist - Stock type: Passbook - Book status: Assigned to teller - Confirm status: Confirmed - Status of stock leaves: Normal - Belongs to teller does this transaction Deposit account - Deposit type: Saving - Deposit status: New/ Normal/ Dormant - Have no passbook Fee collect method is Deposit - Deposit type is Current - Deposit status: Normal - Available balance >= Total fee amount - Same currency with account is issued stock 1. Open "Deposit savings book issue" screen 2. Input Account number 3. Input Serial no 4. Add fee 5. Click Accept | F49: Transaction successfully - Update in stock: + Books have status "Normal". (BookStatus) + Ref account no (RefAccountNo) + Allow print receipt - Update in deposit account: + Passbook number (PassbookOrReceiptNumber) + Passbook status (PassbookOrReceiptStatus) + Deposit status (DepositStatus) + Ref. account No. (Udfield1) - Update deposit account for collect fee | G49: + | I49: 45630 | O49: VyHNT
A50: ='Scenario Test'!$A$13 -> DPT_SBI | B50: =VLOOKUP(TestCase!A50,'Scenario Test'!$A$4:$B$125,2,0) -> DPT_SBI: 11802: Deposit saving book issued | C50: DPT_SBI_005 | E50: Books exist - Stock type: Passbook - Book status: Assigned to teller - Confirm status: Confirmed - Status of stock leaves: Normal - Belongs to teller does this transaction Deposit account - Deposit type: Saving - Deposit status: New/ Normal/ Dormant - Have no passbook Fee collect method is Deposit - Deposit type: Saving - Deposit sub type <> Shwe Cash call deposit account - Deposit status: Normal - Available balance >= Total fee amount - Same currency with account is issued stock 1. Open "Deposit savings book issue" screen 2. Input Account number 3. Input Serial no 4. Add fee 5. Click Accept | F50: Transaction successfully - Update in stock: + Books have status "Normal". (BookStatus) + Ref account no (RefAccountNo) + Allow print receipt - Update in deposit account: + Passbook number (PassbookOrReceiptNumber) + Passbook status (PassbookOrReceiptStatus) + Deposit status (DepositStatus) + Ref. account No. (Udfield1) - Update deposit account for collect fee | G50: + | I50: 45630 | O50: VyHNT
A51: ='Scenario Test'!$A$13 -> DPT_SBI | B51: =VLOOKUP(TestCase!A51,'Scenario Test'!$A$4:$B$125,2,0) -> DPT_SBI: 11802: Deposit saving book issued | C51: DPT_SBI_006 | E51: Books exist - Stock type: Passbook - Book status: Assigned to teller - Confirm status: Confirmed - Status of stock leaves: Normal - Belongs to teller does this transaction Deposit account - Deposit type: Saving - Deposit status: New/ Normal/ Dormant - Have no passbook Fee collect method is Accounting - Posting side: Debit/ Both - Account level: 9 - GL currency = Deposit currency - Account group <> Cash - Direct posting: Yes - Branch account = Branch teller 1. Open "Deposit savings book issue" screen 2. Input Account number 3. Input Serial no 4. Add fee 5. Click Accept | F51: Transaction successfully - Update in stock: + Books have status "Normal". (BookStatus) + Ref account no (RefAccountNo) + Allow print receipt - Update in deposit account: + Passbook number (PassbookOrReceiptNumber) + Passbook status (PassbookOrReceiptStatus) + Deposit status (DepositStatus) + Ref. account No. (Udfield1) - Update deposit account for collect fee | G51: + | I51: 45630 | O51: VyHNT
A52: ='Scenario Test'!$A$13 -> DPT_SBI | B52: =VLOOKUP(TestCase!A52,'Scenario Test'!$A$4:$B$125,2,0) -> DPT_SBI: 11802: Deposit saving book issued | C52: DPT_SBI_007 | E52: Account number is empty | F52: Transaction failed Show error message | G52: + | I52: 45630 | O52: VyHNT
A53: ='Scenario Test'!$A$13 -> DPT_SBI | B53: =VLOOKUP(TestCase!A53,'Scenario Test'!$A$4:$B$125,2,0) -> DPT_SBI: 11802: Deposit saving book issued | C53: DPT_SBI_008 | E53: Account number does not exist | F53: Transaction failed Show error message | G53: + | I53: 45630 | O53: VyHNT
A54: ='Scenario Test'!$A$13 -> DPT_SBI | B54: =VLOOKUP(TestCase!A54,'Scenario Test'!$A$4:$B$125,2,0) -> DPT_SBI: 11802: Deposit saving book issued | C54: DPT_SBI_009 | E54: Serial no is empty | F54: Transaction failed Show error message | G54: + | I54: 45630 | O54: VyHNT
A55: ='Scenario Test'!$A$13 -> DPT_SBI | B55: =VLOOKUP(TestCase!A55,'Scenario Test'!$A$4:$B$125,2,0) -> DPT_SBI: 11802: Deposit saving book issued | C55: DPT_SBI_010 | E55: Serial no does not exist | F55: Transaction failed Show error message | G55: + | I55: 45630 | O55: VyHNT
A56: ='Scenario Test'!$A$13 -> DPT_SBI | B56: =VLOOKUP(TestCase!A56,'Scenario Test'!$A$4:$B$125,2,0) -> DPT_SBI: 11802: Deposit saving book issued | C56: DPT_SBI_011 | E56: Books exist - Stock type: <> Passbook - Book status: Assigned to teller - Confirm status: Confirmed - Status of stock leaves: Normal - Belongs to teller does this transaction Deposit account - Deposit type: Saving - Deposit status: New/ Normal/ Dormant - Have no passbook | F56: Transaction failed Show error message | G56: + | I56: 45630 | O56: VyHNT
A57: ='Scenario Test'!$A$13 -> DPT_SBI | B57: =VLOOKUP(TestCase!A57,'Scenario Test'!$A$4:$B$125,2,0) -> DPT_SBI: 11802: Deposit saving book issued | C57: DPT_SBI_012 | E57: Books exist - Stock type: Passbook - Book status <> Assigned to teller - Confirm status: Confirmed - Status of stock leaves: Normal - Belongs to teller does this transaction Deposit account - Deposit type: Saving - Deposit status: New/ Normal/ Dormant - Have no passbook | F57: Transaction failed Show error message | G57: + | I57: 45630 | O57: VyHNT
A58: ='Scenario Test'!$A$13 -> DPT_SBI | B58: =VLOOKUP(TestCase!A58,'Scenario Test'!$A$4:$B$125,2,0) -> DPT_SBI: 11802: Deposit saving book issued | C58: DPT_SBI_013 | E58: Books exist - Stock type: Passbook - Book status: Assigned to teller - Confirm status <> Confirmed - Status of stock leaves: Normal - Belongs to teller does this transaction Deposit account - Deposit type: Saving - Deposit status: New/ Normal/ Dormant - Have no passbook | F58: Transaction failed Show error message | G58: + | I58: 45630 | O58: VyHNT
A59: ='Scenario Test'!$A$13 -> DPT_SBI | B59: =VLOOKUP(TestCase!A59,'Scenario Test'!$A$4:$B$125,2,0) -> DPT_SBI: 11802: Deposit saving book issued | C59: DPT_SBI_014 | E59: Books exist: - Stock type: Passbook - Book status: Assigned to teller - Confirm status: Confirmed - Status of stock leaves <> Normal - Belongs to teller does this transaction Deposit account: - Deposit type: Saving - Deposit status: New/ Normal/ Dormant - Have no passbook | F59: Transaction failed Show error message | G59: + | I59: 45630 | O59: VyHNT
A60: ='Scenario Test'!$A$13 -> DPT_SBI | B60: =VLOOKUP(TestCase!A60,'Scenario Test'!$A$4:$B$125,2,0) -> DPT_SBI: 11802: Deposit saving book issued | C60: DPT_SBI_015 | E60: Books exist - Stock type: Passbook - Book status: Assigned to teller - Confirm status: Confirmed - Status of stock leaves: Normal - NOT belong to teller does this transaction Deposit account - Deposit type: Saving - Deposit status: New/ Normal/ Dormant - Have no passbook 1. Open "Deposit savings book issue" screen 2. Input Account number 3. Input Serial no 4. Click Accept | F60: Transaction failed Show error message | G60: + | H60: check theo hiện trạng trên prod đang không validate | I60: 45630 | O60: VyHNT
A61: ='Scenario Test'!$A$13 -> DPT_SBI | B61: =VLOOKUP(TestCase!A61,'Scenario Test'!$A$4:$B$125,2,0) -> DPT_SBI: 11802: Deposit saving book issued | C61: DPT_SBI_016 | E61: Books exist - Stock type: Passbook - Book status: Assigned to teller - Confirm status: Confirmed - Status of stock leaves: Normal - Belongs to teller does this transaction Deposit account - Deposit type <> Saving - Deposit status: New/ Normal/ Dormant - Have no passbook | F61: Transaction failed Show error message | G61: + | I61: 45630 | O61: VyHNT
A62: ='Scenario Test'!$A$13 -> DPT_SBI | B62: =VLOOKUP(TestCase!A62,'Scenario Test'!$A$4:$B$125,2,0) -> DPT_SBI: 11802: Deposit saving book issued | C62: DPT_SBI_017 | E62: Books exist - Stock type: Passbook - Book status: Assigned to teller - Confirm status: Confirmed - Status of stock leaves: Normal - Belongs to teller does this transaction Deposit account - Deposit type: Saving - Deposit status <> New/ Normal/ Dormant - Have no passbook | F62: Transaction failed Show error message | G62: + | I62: 45630 | O62: VyHNT
A63: ='Scenario Test'!$A$13 -> DPT_SBI | B63: =VLOOKUP(TestCase!A63,'Scenario Test'!$A$4:$B$125,2,0) -> DPT_SBI: 11802: Deposit saving book issued | C63: DPT_SBI_018 | E63: Books exist - Stock type: Passbook - Book status: Assigned to teller - Confirm status: Confirmed - Status of stock leaves: Normal - Belongs to teller does this transaction Deposit account - Deposit type: Saving - Status is New/ Normal - Has passbook with status is Normal | F63: Transaction failed Show error message | G63: + | I63: 45630 | O63: VyHNT
A64: ='Scenario Test'!$A$13 -> DPT_SBI | B64: =VLOOKUP(TestCase!A64,'Scenario Test'!$A$4:$B$125,2,0) -> DPT_SBI: 11802: Deposit saving book issued | C64: DPT_SBI_019 | E64: Books exist - Stock type: Passbook - Book status: Assigned to teller - Confirm status: Confirmed - Status of stock leaves: Normal - Belongs to teller does this transaction Deposit account - Deposit type: Saving - Deposit status: New/ Normal/ Dormant - Have no passbook Fee collect method is Cash - User has NO right to do transaction related to cash | F64: Transaction failed Show error message | G64: + | I64: 45630 | O64: VyHNT
A65: ='Scenario Test'!$A$13 -> DPT_SBI | B65: =VLOOKUP(TestCase!A65,'Scenario Test'!$A$4:$B$125,2,0) -> DPT_SBI: 11802: Deposit saving book issued | C65: DPT_SBI_020 | E65: Books exist - Stock type: Passbook - Book status: Assigned to teller - Confirm status: Confirmed - Status of stock leaves: Normal - Belongs to teller does this transaction Deposit account - Deposit type: Saving - Deposit status: New/ Normal/ Dormant - Have no passbook Fee collect method is Deposit - Deposit type: Fixed deposit - Deposit status: Normal - Available balance >= total fee amount - Same currency with account is issued stock | F65: Transaction failed Show error message | G65: + | I65: 45630 | O65: VyHNT
A66: ='Scenario Test'!$A$13 -> DPT_SBI | B66: =VLOOKUP(TestCase!A66,'Scenario Test'!$A$4:$B$125,2,0) -> DPT_SBI: 11802: Deposit saving book issued | C66: DPT_SBI_021 | E66: Books exist - Stock type: Passbook - Book status: Assigned to teller - Confirm status: Confirmed - Status of stock leaves: Normal - Belongs to teller does this transaction Deposit account - Deposit type: Saving - Status is New/ Normal - Have no passbook - Same branch with stock Fee collect method is Deposit - Deposit type: Current/ Saving - Deposit status <> Normal - Available balance >= total fee amount - Same currency with account is issued stock | F66: Transaction failed Show error message | G66: + | I66: 45630 | O66: VyHNT
A67: ='Scenario Test'!$A$13 -> DPT_SBI | B67: =VLOOKUP(TestCase!A67,'Scenario Test'!$A$4:$B$125,2,0) -> DPT_SBI: 11802: Deposit saving book issued | C67: DPT_SBI_022 | E67: Books exist - Stock type: Passbook - Book status: Assigned to teller - Confirm status: Confirmed - Status of stock leaves: Normal - Belongs to teller does this transaction Deposit account - Deposit type: Saving - Deposit status: New/ Normal/ Dormant - Have no passbook Fee collect method is Deposit - Deposit type: Current/ Saving - Deposit status: Normal - Available balance < Total fee amount - Same currency with account is issued stock | F67: Transaction failed Show error message | G67: + | I67: 45630 | O67: VyHNT
A68: ='Scenario Test'!$A$13 -> DPT_SBI | B68: =VLOOKUP(TestCase!A68,'Scenario Test'!$A$4:$B$125,2,0) -> DPT_SBI: 11802: Deposit saving book issued | C68: DPT_SBI_023 | E68: Books exist - Stock type: Passbook - Book status: Assigned to teller - Confirm status: Confirmed - Status of stock leaves: Normal - Belongs to teller does this transaction Deposit account - Deposit type: Saving - Deposit status: New/ Normal/ Dormant - Have no passbook Fee collect method is Deposit - Deposit type: Current/ Saving - Deposit status: Normal - Available balance >= Total fee amount - Currency different with account is issued stock | F68: Transaction failed Show error message | G68: + | I68: 45630 | O68: VyHNT
A69: ='Scenario Test'!$A$13 -> DPT_SBI | B69: =VLOOKUP(TestCase!A69,'Scenario Test'!$A$4:$B$125,2,0) -> DPT_SBI: 11802: Deposit saving book issued | C69: DPT_SBI_024 | E69: Books exist - Stock type: Passbook - Book status: Assigned to teller - Confirm status: Confirmed - Status of stock leaves: Normal - Belongs to teller does this transaction Deposit account - Deposit type: Saving - Deposit status: New/ Normal/ Dormant - Have no passbook Fee collect method is Accounting - Posting side: Credit - Account level: 9 - GL currency = Deposit currency - Account group <> Cash - Direct posting: Yes - Branch account = Branch teller | F69: Transaction failed Show error message | G69: + | H69: check theo hiện trạng trên prod đang không validate | I69: 45630 | O69: VyHNT
A70: ='Scenario Test'!$A$13 -> DPT_SBI | B70: =VLOOKUP(TestCase!A70,'Scenario Test'!$A$4:$B$125,2,0) -> DPT_SBI: 11802: Deposit saving book issued | C70: DPT_SBI_025 | E70: Books exist - Stock type: Passbook - Book status: Assigned to teller - Confirm status: Confirmed - Status of stock leaves: Normal - Belongs to teller does this transaction Deposit account - Deposit type: Saving - Deposit status: New/ Normal/ Dormant - Have no passbook Fee collect method is Accounting - Posting side: Debit/ Both - Account level <> 9 - GL currency = Deposit currency - Account group <> Cash - Direct posting: Yes - Branch account = Branch teller | F70: Transaction failed Show error message | G70: + | I70: 45630 | O70: VyHNT
A71: ='Scenario Test'!$A$13 -> DPT_SBI | B71: =VLOOKUP(TestCase!A71,'Scenario Test'!$A$4:$B$125,2,0) -> DPT_SBI: 11802: Deposit saving book issued | C71: DPT_SBI_026 | E71: Books exist - Stock type: Passbook - Book status: Assigned to teller - Confirm status: Confirmed - Status of stock leaves: Normal - Belongs to teller does this transaction Deposit account - Deposit type: Saving - Deposit status: New/ Normal/ Dormant - Have no passbook Fee collect method is Accounting - Posting side: Debit/ Both - Account level: 9 - GL currency <> Deposit currency - Account group <> Cash - Direct posting: Yes - Branch account = Branch teller | F71: Transaction failed Show error message | G71: + | I71: 45630 | O71: VyHNT
A72: ='Scenario Test'!$A$13 -> DPT_SBI | B72: =VLOOKUP(TestCase!A72,'Scenario Test'!$A$4:$B$125,2,0) -> DPT_SBI: 11802: Deposit saving book issued | C72: DPT_SBI_027 | E72: Books exist - Stock type: Passbook - Book status: Assigned to teller - Confirm status: Confirmed - Status of stock leaves: Normal - Belongs to teller does this transaction Deposit account - Deposit type: Saving - Deposit status: New/ Normal/ Dormant - Have no passbook Fee collect method is Accounting - Posting side: Debit/ Both - Account level: 9 - GL currency = Deposit currency - Account group: Cash - Direct posting: Yes - Branch account = Branch teller | F72: Transaction failed Show error message | G72: + | I72: 45630 | O72: VyHNT
A73: ='Scenario Test'!$A$13 -> DPT_SBI | B73: =VLOOKUP(TestCase!A73,'Scenario Test'!$A$4:$B$125,2,0) -> DPT_SBI: 11802: Deposit saving book issued | C73: DPT_SBI_028 | E73: Books exist - Stock type: Passbook - Book status: Assigned to teller - Confirm status: Confirmed - Status of stock leaves: Normal - Belongs to teller does this transaction Deposit account - Deposit type: Saving - Deposit status: New/ Normal/ Dormant - Have no passbook Fee collect method is Accounting - Posting side: Debit/ Both - Account level: 9 - GL currency = Deposit currency - Account group <> Cash - Direct posting <> Yes - Branch account = Branch teller | F73: Transaction failed Show error message | G73: + | I73: 45630 | O73: VyHNT
A74: ='Scenario Test'!$A$13 -> DPT_SBI | B74: =VLOOKUP(TestCase!A74,'Scenario Test'!$A$4:$B$125,2,0) -> DPT_SBI: 11802: Deposit saving book issued | C74: DPT_SBI_029 | E74: Books exist - Stock type: Passbook - Book status: Assigned to teller - Confirm status: Confirmed - Status of stock leaves: Normal - Belongs to teller does this transaction Deposit account - Deposit type: Saving - Deposit status: New/ Normal/ Dormant - Have no passbook Fee collect method is Accounting - Posting side: Debit/ Both - Account level: 9 - GL currency = Deposit currency - Account group <> Cash - Direct posting: Yes - Branch account <> Branch teller | F74: Transaction failed Show error message | G74: + | I74: 45630 | O74: VyHNT
A75: ='Scenario Test'!$A$13 -> DPT_SBI | B75: =VLOOKUP(TestCase!A75,'Scenario Test'!$A$4:$B$125,2,0) -> DPT_SBI: 11802: Deposit saving book issued | C75: DPT_SBI_030 | E75: Reverse transaction | F75: Reverse successfully Return back to data before do transaction | G75: + | I75: 45630 | O75: VyHNT
A76: ='Scenario Test'!$A$14 -> DPT_FBI | B76: =VLOOKUP(TestCase!A76,'Scenario Test'!$A$4:$B$125,2,0) -> DPT_FBI: 11804: Fixed deposit book issue
A77: ='Scenario Test'!$A$14 -> DPT_FBI | B77: =VLOOKUP(TestCase!A77,'Scenario Test'!$A$4:$B$125,2,0) -> DPT_FBI: 11804: Fixed deposit book issue | C77: DPT_FBI_001 | E77: Books exist - Stock type: Passbook - Book status: Assigned to teller - Confirm status: Confirmed - Status of stock leaves: Normal - Belongs to teller does this transaction Deposit account - Deposit type: Fixed deposit - Deposit sub type <> Prepaid fixed depsoit account - Deposit status: New/ Normal/ Dormant/ Maturity - Have no passbook 1. Open "Fixed deposit book issue" screen 2. Input Account number 3. Input Serial no 4. Click Accept | F77: Transaction successfully - Update in stock: + Books have status "Normal". (BookStatus) + Ref account no (RefAccountNo) + Allow print receipt - Update in deposit account: + Passbook number (PassbookOrReceiptNumber) + Passbook status (PassbookOrReceiptStatus) + Deposit status (DepositStatus) + Ref. account No. (Udfield1) | G77: + | I77: 45631 | O77: VyHNT
A78: ='Scenario Test'!$A$14 -> DPT_FBI | B78: =VLOOKUP(TestCase!A78,'Scenario Test'!$A$4:$B$125,2,0) -> DPT_FBI: 11804: Fixed deposit book issue | C78: DPT_FBI_002 | E78: Books exist - Stock type: Passbook - Book status: Assigned to teller - Confirm status: Confirmed - Status of stock leaves: Normal - Belongs to teller does this transaction Deposit account - Deposit type: Fixed deposit - Deposit sub type <> Prepaid fixed depsoit account - Deposit status: New/ Normal/ Dormant/ Maturity - Already has passbook with status <> Normal 1. Open "Fixed deposit book issue" screen 2. Input Account number 3. Input Serial no 4. Click Accept | F78: Transaction successfully - Update in stock: + Books have status "Normal". (BookStatus) + Ref account no (RefAccountNo) + Allow print receipt - Update in deposit account: + Passbook number (PassbookOrReceiptNumber) + Passbook status (PassbookOrReceiptStatus) + Deposit status (DepositStatus) + Ref. account No. (Udfield1) | G78: + | I78: 45631 | O78: VyHNT
A79: ='Scenario Test'!$A$14 -> DPT_FBI | B79: =VLOOKUP(TestCase!A79,'Scenario Test'!$A$4:$B$125,2,0) -> DPT_FBI: 11804: Fixed deposit book issue | C79: DPT_FBI_003 | E79: Books exist - Stock type: Passbook - Book status: Assigned to teller - Confirm status: Confirmed - Status of stock leaves: Normal - Belongs to teller does this transaction Deposit account - Deposit type: Fixed deposit - Deposit sub type <> Prepaid fixed depsoit account - Deposit status: New/ Normal/ Dormant/ Maturity - Have no passbook Fee collect method is Cash - User has right to do transaction related to cash 1. Open "Fixed deposit book issue" screen 2. Input Account number 3. Input Serial no 4. Add fee 5. Click Accept | F79: Transaction successfully - Update in stock: + Books have status "Normal". (BookStatus) + Ref account no (RefAccountNo) + Allow print receipt - Update in deposit account: + Passbook number (PassbookOrReceiptNumber) + Passbook status (PassbookOrReceiptStatus) + Deposit status (DepositStatus) + Ref. account No. (Udfield1) - Update cash flow | G79: + | I79: 45631 | O79: VyHNT
A80: ='Scenario Test'!$A$14 -> DPT_FBI | B80: =VLOOKUP(TestCase!A80,'Scenario Test'!$A$4:$B$125,2,0) -> DPT_FBI: 11804: Fixed deposit book issue | C80: DPT_FBI_004 | E80: Books exist - Stock type: Passbook - Book status: Assigned to teller - Confirm status: Confirmed - Status of stock leaves: Normal - Belongs to teller does this transaction Deposit account - Deposit type: Fixed deposit - Deposit sub type <> Prepaid fixed depsoit account - Deposit status: New/ Normal/ Dormant/ Maturity - Have no passbook Fee collect method is Deposit - Deposit type: Current - Deposit status: Normal - Available balance >= total fee amount - Same currency with account is issued stock 1. Open "Fixed deposit book issue" screen 2. Input Account number 3. Input Serial no 4. Add fee 5. Click Accept | F80: Transaction successfully - Update in stock: + Books have status "Normal". (BookStatus) + Ref account no (RefAccountNo) + Allow print receipt - Update in deposit account: + Passbook number (PassbookOrReceiptNumber) + Passbook status (PassbookOrReceiptStatus) + Deposit status (DepositStatus) + Ref. account No. (Udfield1) - Update deposit account for collect fee | G80: + | I80: 45631 | O80: VyHNT
A81: ='Scenario Test'!$A$14 -> DPT_FBI | B81: =VLOOKUP(TestCase!A81,'Scenario Test'!$A$4:$B$125,2,0) -> DPT_FBI: 11804: Fixed deposit book issue | C81: DPT_FBI_005 | E81: Books exist - Stock type: Passbook - Book status: Assigned to teller - Confirm status: Confirmed - Status of stock leaves: Normal - Belongs to teller does this transaction Deposit account - Deposit type: Fixed deposit - Deposit sub type <> Prepaid fixed depsoit account - Deposit status: New/ Normal/ Dormant/ Maturity - Have no passbook Fee collect method is Accounting - Posting side: Debit/ Both - Account level: 9 - GL currency = Deposit currency - Account group <> Cash - Direct posting: Yes 1. Open "Fixed deposit book issue" screen 2. Input Account number 3. Input Serial no 4. Add fee 5. Click Accept | F81: Transaction successfully - Update in stock: + Books have status "Normal". (BookStatus) + Ref account no (RefAccountNo) + Allow print receipt - Update in deposit account: + Passbook number (PassbookOrReceiptNumber) + Passbook status (PassbookOrReceiptStatus) + Deposit status (DepositStatus) + Ref. account No. (Udfield1) - Update deposit account for collect fee | G81: + | I81: 45631 | O81: VyHNT
A82: ='Scenario Test'!$A$14 -> DPT_FBI | B82: =VLOOKUP(TestCase!A82,'Scenario Test'!$A$4:$B$125,2,0) -> DPT_FBI: 11804: Fixed deposit book issue | C82: DPT_FBI_006 | E82: Account number is empty | F82: Transaction failed Show error message | G82: + | I82: 45631 | O82: VyHNT
A83: ='Scenario Test'!$A$14 -> DPT_FBI | B83: =VLOOKUP(TestCase!A83,'Scenario Test'!$A$4:$B$125,2,0) -> DPT_FBI: 11804: Fixed deposit book issue | C83: DPT_FBI_007 | E83: Account number does not exist | F83: Transaction failed Show error message | G83: + | I83: 45631 | O83: VyHNT
A84: ='Scenario Test'!$A$14 -> DPT_FBI | B84: =VLOOKUP(TestCase!A84,'Scenario Test'!$A$4:$B$125,2,0) -> DPT_FBI: 11804: Fixed deposit book issue | C84: DPT_FBI_008 | E84: Serial no is empty | F84: Transaction failed Show error message | G84: + | I84: 45631 | O84: VyHNT
A85: ='Scenario Test'!$A$14 -> DPT_FBI | B85: =VLOOKUP(TestCase!A85,'Scenario Test'!$A$4:$B$125,2,0) -> DPT_FBI: 11804: Fixed deposit book issue | C85: DPT_FBI_009 | E85: Serial no does not exist | F85: Transaction failed Show error message | G85: + | I85: 45631 | O85: VyHNT
A86: ='Scenario Test'!$A$14 -> DPT_FBI | B86: =VLOOKUP(TestCase!A86,'Scenario Test'!$A$4:$B$125,2,0) -> DPT_FBI: 11804: Fixed deposit book issue | C86: DPT_FBI_010 | E86: Books exist - Stock type: <> Passbook - Book status: Assigned to teller - Confirm status: Confirmed - Status of stock leaves: Normal - Belongs to teller does this transaction Deposit account - Deposit type: Fixed deposit - Deposit sub type <> Prepaid fixed depsoit account - Deposit status: New/ Normal/ Dormant/ Maturity - Have no passbook | F86: Transaction failed Show error message | G86: + | I86: 45631 | O86: VyHNT
A87: ='Scenario Test'!$A$14 -> DPT_FBI | B87: =VLOOKUP(TestCase!A87,'Scenario Test'!$A$4:$B$125,2,0) -> DPT_FBI: 11804: Fixed deposit book issue | C87: DPT_FBI_011 | E87: Books exist: - Stock type: Passbook - Book status <> Assigned to teller - Confirm status: Confirmed - Status of stock leaves: Normal - Belongs to teller does this transaction Deposit account - Deposit type: Fixed deposit - Deposit sub type <> Prepaid fixed depsoit account - Deposit status: New/ Normal/ Dormant/ Maturity - Have no passbook | F87: Transaction failed Show error message | G87: + | I87: 45631 | O87: VyHNT
A88: ='Scenario Test'!$A$14 -> DPT_FBI | B88: =VLOOKUP(TestCase!A88,'Scenario Test'!$A$4:$B$125,2,0) -> DPT_FBI: 11804: Fixed deposit book issue | C88: DPT_FBI_012 | E88: Books exist - Stock type: Passbook - Book status: Assigned to teller - Confirm status <> Confirmed - Status of stock leaves: Normal - Belongs to teller does this transaction Deposit account - Deposit type: Fixed deposit - Deposit sub type <> Prepaid fixed depsoit account - Deposit status: New/ Normal/ Dormant/ Maturity - Have no passbook | F88: Transaction failed Show error message | G88: + | I88: 45631 | O88: VyHNT
A89: ='Scenario Test'!$A$14 -> DPT_FBI | B89: =VLOOKUP(TestCase!A89,'Scenario Test'!$A$4:$B$125,2,0) -> DPT_FBI: 11804: Fixed deposit book issue | C89: DPT_FBI_013 | E89: Books exist - Stock type: Passbook - Book status: Assigned to teller - Confirm status: Confirmed - Status of stock leaves <> Normal - Belongs to teller does this transaction Deposit account - Deposit type: Fixed deposit - Deposit sub type <> Prepaid fixed depsoit account - Deposit status: New/ Normal/ Dormant/ Maturity - Have no passbook | F89: Transaction failed Show error message | G89: + | I89: 45631 | O89: VyHNT
A90: ='Scenario Test'!$A$14 -> DPT_FBI | B90: =VLOOKUP(TestCase!A90,'Scenario Test'!$A$4:$B$125,2,0) -> DPT_FBI: 11804: Fixed deposit book issue | C90: DPT_FBI_014 | E90: Books exist - Stock type: Passbook - Book status: Assigned to teller - Confirm status: Confirmed - Status of stock leaves: Normal - NOT belong to teller does this transaction Deposit account - Deposit type: Fixed deposit - Deposit sub type <> Prepaid fixed depsoit account - Deposit status: New/ Normal/ Dormant/ Maturity - Have no passbook | F90: Transaction failed Show error message | G90: + | H90: check theo hiện trạng trên prod đang không validate | I90: 45631 | O90: VyHNT
A91: ='Scenario Test'!$A$14 -> DPT_FBI | B91: =VLOOKUP(TestCase!A91,'Scenario Test'!$A$4:$B$125,2,0) -> DPT_FBI: 11804: Fixed deposit book issue | C91: DPT_FBI_015 | E91: Books exist - Stock type: Passbook - Book status: Assigned to teller - Confirm status: Confirmed - Status of stock leaves: Normal - Belongs to teller does this transaction Deposit account - Deposit type <> Fixed deposit - Deposit status: New/ Normal/ Dormant/ Maturity - Have no passbook | F91: Transaction failed Show error message | G91: + | I91: 45631 | O91: VyHNT
A92: ='Scenario Test'!$A$14 -> DPT_FBI | B92: =VLOOKUP(TestCase!A92,'Scenario Test'!$A$4:$B$125,2,0) -> DPT_FBI: 11804: Fixed deposit book issue | C92: DPT_FBI_016 | E92: Books exist - Stock type: Passbook - Book status: Assigned to teller - Confirm status: Confirmed - Status of stock leaves: Normal - Belongs to teller does this transaction Deposit account - Deposit type: Fixed deposit - Deposit sub type: Prepaid fixed depsoit account - Deposit status: New/ Normal/ Dormant/ Maturity - Have no passbook | F92: Transaction failed Show error message | G92: + | I92: 45631 | O92: VyHNT
A93: ='Scenario Test'!$A$14 -> DPT_FBI | B93: =VLOOKUP(TestCase!A93,'Scenario Test'!$A$4:$B$125,2,0) -> DPT_FBI: 11804: Fixed deposit book issue | C93: DPT_FBI_017 | E93: Books exist - Stock type: Passbook - Book status: Assigned to teller - Confirm status: Confirmed - Status of stock leaves: Normal - Belongs to teller does this transaction Deposit account - Deposit type: Fixed deposit - Deposit sub type <> Prepaid fixed depsoit account - Deposit status <> New/ Normal/ Dormant/ Maturity - Have no passbook | F93: Transaction failed Show error message | G93: + | I93: 45631 | O93: VyHNT
A94: ='Scenario Test'!$A$14 -> DPT_FBI | B94: =VLOOKUP(TestCase!A94,'Scenario Test'!$A$4:$B$125,2,0) -> DPT_FBI: 11804: Fixed deposit book issue | C94: DPT_FBI_018 | E94: Books exist - Stock type: Passbook - Book status: Assigned to teller - Confirm status: Confirmed - Status of stock leaves: Normal - Belongs to teller does this transaction Deposit account - Deposit type: Fixed deposit - Deposit sub type <> Prepaid fixed depsoit account - Deposit status: New/ Normal/ Dormant/ Maturity - Has passbook with status is Normal | F94: Transaction failed Show error message | G94: + | I94: 45631 | O94: VyHNT
A95: ='Scenario Test'!$A$14 -> DPT_FBI | B95: =VLOOKUP(TestCase!A95,'Scenario Test'!$A$4:$B$125,2,0) -> DPT_FBI: 11804: Fixed deposit book issue | C95: DPT_FBI_019 | E95: Books exist - Stock type: Passbook - Book status: Assigned to teller - Confirm status: Confirmed - Status of stock leaves: Normal - Belongs to teller does this transaction Deposit account - Deposit type: Fixed deposit - Deposit sub type <> Prepaid fixed depsoit account - Deposit status: New/ Normal/ Dormant/ Maturity - Have no passbook Fee collect method is Cash - User has NO right to do transaction related to cash | F95: Transaction failed Show error message | G95: + | I95: 45631 | O95: VyHNT
A96: ='Scenario Test'!$A$14 -> DPT_FBI | B96: =VLOOKUP(TestCase!A96,'Scenario Test'!$A$4:$B$125,2,0) -> DPT_FBI: 11804: Fixed deposit book issue | C96: DPT_FBI_020 | E96: Books exist - Stock type: Passbook - Book status: Assigned to teller - Confirm status: Confirmed - Status of stock leaves: Normal - Belongs to teller does this transaction Deposit account - Deposit type: Fixed deposit - Deposit sub type <> Prepaid fixed depsoit account - Status is New/ Normal/ Actived - Have no passbook - Same branch with stock Fee collect method is Deposit - Deposit type: Fixed deposit - Deposit status: Normal - Available balance >= total fee amount - Same currency with account is issued stock | F96: Transaction failed Show error message | G96: + | I96: 45631 | O96: VyHNT
A97: ='Scenario Test'!$A$14 -> DPT_FBI | B97: =VLOOKUP(TestCase!A97,'Scenario Test'!$A$4:$B$125,2,0) -> DPT_FBI: 11804: Fixed deposit book issue | C97: DPT_FBI_021 | E97: Books exist - Stock type: Passbook - Book status: Assigned to teller - Confirm status: Confirmed - Status of stock leaves: Normal - Belongs to teller does this transaction Deposit account - Deposit type: Fixed deposit - Deposit sub type <> Prepaid fixed depsoit account - Deposit status: New/ Normal/ Dormant/ Maturity - Have no passbook Fee collect method is Deposit - Deposit type: Current/ Saving - Deposit status <> Normal - Available balance >= Total fee amount - Same currency with account is issued stock | F97: Transaction failed Show error message | G97: + | I97: 45631 | O97: VyHNT
A98: ='Scenario Test'!$A$14 -> DPT_FBI | B98: =VLOOKUP(TestCase!A98,'Scenario Test'!$A$4:$B$125,2,0) -> DPT_FBI: 11804: Fixed deposit book issue | C98: DPT_FBI_022 | E98: Books exist - Stock type: Passbook - Book status: Assigned to teller - Confirm status: Confirmed - Status of stock leaves: Normal - Belongs to teller does this transaction Deposit account - Deposit type: Fixed deposit - Deposit sub type <> Prepaid fixed depsoit account - Deposit status: New/ Normal/ Dormant/ Maturity - Have no passbook Fee collect method is Deposit - Deposit type is Current/ Saving - Deposit status: Normal - Available balance < total fee amount - Same currency with account is issued stock | F98: Transaction failed Show error message | G98: + | I98: 45631 | O98: VyHNT
A99: ='Scenario Test'!$A$14 -> DPT_FBI | B99: =VLOOKUP(TestCase!A99,'Scenario Test'!$A$4:$B$125,2,0) -> DPT_FBI: 11804: Fixed deposit book issue | C99: DPT_FBI_023 | E99: Books exist - Stock type: Passbook - Book status: Assigned to teller - Confirm status: Confirmed - Status of stock leaves: Normal - Belongs to teller does this transaction Deposit account - Deposit type: Fixed deposit - Deposit sub type <> Prepaid fixed depsoit account - Deposit status: New/ Normal/ Dormant/ Maturity - Have no passbook Fee collect method is Deposit - Deposit type is Current/ Saving - Deposit status: Normal - Available balance >= Total fee amount - Currency different with account is issued stock | F99: Transaction failed Show error message | G99: + | I99: 45631 | O99: VyHNT
A100: ='Scenario Test'!$A$14 -> DPT_FBI | B100: =VLOOKUP(TestCase!A100,'Scenario Test'!$A$4:$B$125,2,0) -> DPT_FBI: 11804: Fixed deposit book issue | C100: DPT_FBI_024 | E100: Books exist: - Stock type: Passbook - Book status: Assigned to teller - Confirm status: Confirmed - Status of stock leaves: Normal - Belongs to teller does this transaction Deposit account - Deposit type: Fixed deposit - Deposit sub type <> Prepaid fixed depsoit account - Deposit status: New/ Normal/ Dormant/ Maturity - Have no passbook Fee collect method is Accounting - Posting side: Credit - Account level: 9 - GL currency = Deposit currency - Account group <> Cash - Direct posting: Yes | F100: Transaction failed Show error message | G100: + | H100: check theo hiện trạng trên prod đang không validate | I100: 45631 | O100: VyHNT
A101: ='Scenario Test'!$A$14 -> DPT_FBI | B101: =VLOOKUP(TestCase!A101,'Scenario Test'!$A$4:$B$125,2,0) -> DPT_FBI: 11804: Fixed deposit book issue | C101: DPT_FBI_025 | E101: Books exist: - Stock type: Passbook - Book status: Assigned to teller - Confirm status: Confirmed - Status of stock leaves: Normal - Belongs to teller does this transaction Deposit account - Deposit type: Fixed deposit - Deposit sub type <> Prepaid fixed depsoit account - Deposit status: New/ Normal/ Dormant/ Maturity - Have no passbook Fee collect method is Accounting - Posting side: Debit/ Both - Account level <> 9 - GL currency = Deposit currency - Account group <> Cash - Direct posting: Yes | F101: Transaction failed Show error message | G101: + | I101: 45631 | O101: VyHNT
A102: ='Scenario Test'!$A$14 -> DPT_FBI | B102: =VLOOKUP(TestCase!A102,'Scenario Test'!$A$4:$B$125,2,0) -> DPT_FBI: 11804: Fixed deposit book issue | C102: DPT_FBI_026 | E102: Books exist: - Stock type: Passbook - Book status: Assigned to teller - Confirm status: Confirmed - Status of stock leaves: Normal - Belongs to teller does this transaction Deposit account - Deposit type: Fixed deposit - Deposit sub type <> Prepaid fixed depsoit account - Deposit status: New/ Normal/ Dormant/ Maturity - Have no passbook Fee collect method is Accounting - Posting side: Debit/ Both - Account level: 9 - GL currency <> Deposit currency - Account group <> Cash - Direct posting: Yes | F102: Transaction failed Show error message | G102: + | H102: check theo hiện trạng trên prod đang không validate | I102: 45631 | O102: VyHNT
A103: ='Scenario Test'!$A$14 -> DPT_FBI | B103: =VLOOKUP(TestCase!A103,'Scenario Test'!$A$4:$B$125,2,0) -> DPT_FBI: 11804: Fixed deposit book issue | C103: DPT_FBI_027 | E103: Books exist: - Stock type: Passbook - Book status: Assigned to teller - Confirm status: Confirmed - Status of stock leaves: Normal - Belongs to teller does this transaction Deposit account - Deposit type: Fixed deposit - Deposit sub type <> Prepaid fixed depsoit account - Deposit status: New/ Normal/ Dormant/ Maturity - Have no passbook Fee collect method is Accounting - Posting side: Debit/ Both - Account level: 9 - GL currency = Deposit currency - Account group: Cash - Direct posting: Yes | F103: Transaction failed Show error message | G103: + | I103: 45631 | O103: VyHNT
A104: ='Scenario Test'!$A$14 -> DPT_FBI | B104: =VLOOKUP(TestCase!A104,'Scenario Test'!$A$4:$B$125,2,0) -> DPT_FBI: 11804: Fixed deposit book issue | C104: DPT_FBI_028 | E104: Books exist - Stock type: Passbook - Book status: Assigned to teller - Confirm status: Confirmed - Status of stock leaves: Normal - Belongs to teller does this transaction Deposit account - Deposit type: Fixed deposit - Deposit sub type <> Prepaid fixed depsoit account - Deposit status: New/ Normal/ Dormant/ Maturity - Have no passbook Fee collect method is Accounting - Posting side: Debit/ Both - Account level: 9 - GL currency = Deposit currency - Account group <> Cash - Direct posting <> Yes | F104: Transaction failed Show error message | G104: + | I104: 45631 | O104: VyHNT
A105: ='Scenario Test'!$A$14 -> DPT_FBI | B105: =VLOOKUP(TestCase!A105,'Scenario Test'!$A$4:$B$125,2,0) -> DPT_FBI: 11804: Fixed deposit book issue | C105: DPT_FBI_029 | E105: Reverse transaction | F105: Reverse successfully Return back to data before do transaction | G105: + | I105: 45631 | O105: VyHNT
A106: ='Scenario Test'!$A$15 -> DPT_CER | B106: =VLOOKUP(TestCase!A106,'Scenario Test'!$A$4:$B$125,2,0) -> DPT_CER: 11803: Fixed deposit receipt issue
A107: ='Scenario Test'!$A$15 -> DPT_CER | B107: =VLOOKUP(TestCase!A107,'Scenario Test'!$A$4:$B$125,2,0) -> DPT_CER: 11803: Fixed deposit receipt issue | C107: DPT_CER_001 | E107: Books exist: - Stock type: Receipt - Book status: Assigned to teller - Confirm status: Confirmed - Status of stock leaves: Normal - Belongs to teller does this transaction Deposit account - Deposit type: Fixed deposit - Deposit sub type: Prepaid fixed depsoit account - Deposit status: New/ Normal/ Dormant/ Maturity - Have no receipt 1. Open "Fixed deposit receipt issued" screen 2. Input Account number 3. Input Cerfiticate serial 4. Click Accept | F107: Transaction successfully - Update in stock: + Books have status "Normal". (BookStatus) + Ref account no (RefAccountNo) + Allow print receipt - Update in deposit account: + Passbook number (PassbookOrReceiptNumber) + Passbook status (PassbookOrReceiptStatus) + Deposit status (DepositStatus) + Ref. account No. (Udfield1) | G107: + | I107: 45631 | O107: VyHNT
A108: ='Scenario Test'!$A$15 -> DPT_CER | B108: =VLOOKUP(TestCase!A108,'Scenario Test'!$A$4:$B$125,2,0) -> DPT_CER: 11803: Fixed deposit receipt issue | C108: DPT_CER_002 | E108: Books exist - Stock type: Receipt - Book status: Assigned to teller - Confirm status: Confirmed - Status of stock leaves: Normal - Belongs to teller does this transaction Deposit account - Deposit type: Fixed deposit - Deposit sub type: Prepaid fixed depsoit account - Deposit status: New/ Normal/ Dormant/ Maturity - Already has receipt with status <> Normal 1. Open "Fixed deposit receipt issued" screen 2. Input Account number 3. Input Cerfiticate serial 4. Click Accept | F108: Transaction successfully - Update in stock: + Books have status "Normal". (BookStatus) + Ref account no (RefAccountNo) + Allow print receipt - Update in deposit account: + Passbook number (PassbookOrReceiptNumber) + Passbook status (PassbookOrReceiptStatus) + Deposit status (DepositStatus) + Ref. account No. (Udfield1) | G108: + | I108: 45631 | O108: VyHNT
A109: ='Scenario Test'!$A$15 -> DPT_CER | B109: =VLOOKUP(TestCase!A109,'Scenario Test'!$A$4:$B$125,2,0) -> DPT_CER: 11803: Fixed deposit receipt issue | C109: DPT_CER_003 | E109: Books exist: - Stock type: Receipt - Book status: Assigned to teller - Confirm status: Confirmed - Status of stock leaves: Normal - Belongs to teller does this transaction Deposit account - Deposit type: Fixed deposit - Deposit sub type: Prepaid fixed depsoit account - Deposit status: New/ Normal/ Dormant/ Maturity - Have no receipt Fee collect method is Cash - User has right to do transaction related to cash 1. Open "Fixed deposit receipt issued" screen 2. Input Account number 3. Input Cerfiticate serial 4. Add fee 5. Click Accept | F109: Transaction successfully - Update in stock: + Books have status "Normal". (BookStatus) + Ref account no (RefAccountNo) + Allow print receipt - Update in deposit account: + Passbook number (PassbookOrReceiptNumber) + Passbook status (PassbookOrReceiptStatus) + Deposit status (DepositStatus) + Ref. account No. (Udfield1) - Update cash flow | G109: + | I109: 45631 | O109: VyHNT
A110: ='Scenario Test'!$A$15 -> DPT_CER | B110: =VLOOKUP(TestCase!A110,'Scenario Test'!$A$4:$B$125,2,0) -> DPT_CER: 11803: Fixed deposit receipt issue | C110: DPT_CER_004 | E110: Books exist - Stock type: Receipt - Book status: Assigned to teller - Confirm status: Confirmed - Status of stock leaves: Normal - Belongs to teller does this transaction Deposit account - Deposit type: Fixed deposit - Deposit sub type: Prepaid fixed depsoit account - Deposit status: New/ Normal/ Dormant/ Maturity - Have no receipt Fee collect method is Deposit - Deposit type: Current - Deposit status: Normal - Available balance >= Total fee amount - Same currency with account is issued stock 1. Open "Fixed deposit receipt issued" screen 2. Input Account number 3. Input Cerfiticate serial 4. Add fee 5. Click Accept | F110: Transaction successfully - Update in stock: + Books have status "Normal". (BookStatus) + Ref account no (RefAccountNo) + Allow print receipt - Update in deposit account: + Passbook number (PassbookOrReceiptNumber) + Passbook status (PassbookOrReceiptStatus) + Deposit status (DepositStatus) + Ref. account No. (Udfield1) - Update deposit account for collect fee | G110: + | I110: 45631 | O110: VyHNT
A111: ='Scenario Test'!$A$15 -> DPT_CER | B111: =VLOOKUP(TestCase!A111,'Scenario Test'!$A$4:$B$125,2,0) -> DPT_CER: 11803: Fixed deposit receipt issue | C111: DPT_CER_005 | E111: Books exist - Stock type: Receipt - Book status: Assigned to teller - Confirm status: Confirmed - Status of stock leaves: Normal - Belongs to teller does this transaction Deposit account - Deposit type: Fixed deposit - Deposit sub type: Prepaid fixed depsoit account - Deposit status: New/ Normal/ Dormant/ Maturity - Have no receipt Fee collect method is Deposit - Deposit type: Saving - Deposit status: Normal - Available balance >= Total fee amount - Same currency with account is issued stock 1. Open "Fixed deposit receipt issued" screen 2. Input Account number 3. Input Cerfiticate serial 4. Add fee 5. Click Accept | F111: Transaction successfully - Update in stock: + Books have status "Normal". (BookStatus) + Ref account no (RefAccountNo) + Allow print receipt - Update in deposit account: + Passbook number (PassbookOrReceiptNumber) + Passbook status (PassbookOrReceiptStatus) + Deposit status (DepositStatus) + Ref. account No. (Udfield1) - Update deposit account for collect fee | G111: + | I111: 45631 | O111: VyHNT
A112: ='Scenario Test'!$A$15 -> DPT_CER | B112: =VLOOKUP(TestCase!A112,'Scenario Test'!$A$4:$B$125,2,0) -> DPT_CER: 11803: Fixed deposit receipt issue | C112: DPT_CER_006 | E112: Books exist - Stock type: Receipt - Book status: Assigned to teller - Confirm status: Confirmed - Status of stock leaves: Normal - Belongs to teller does this transaction Deposit account - Deposit type: Fixed deposit - Deposit sub type: Prepaid fixed depsoit account - Deposit status: New/ Normal/ Dormant/ Maturity - Have no receipt Fee collect method is Accounting - Posting side: Debit/ Both - Account level: 9 - GL currency = Deposit currency - Account group <> Cash - Direct posting: Yes 1. Open "Fixed deposit receipt issued" screen 2. Input Account number 3. Input Cerfiticate serial 4. Add fee 5. Click Accept | F112: Transaction successfully - Update in stock: + Books have status "Normal". (BookStatus) + Ref account no (RefAccountNo) + Allow print receipt - Update in deposit account: + Passbook number (PassbookOrReceiptNumber) + Passbook status (PassbookOrReceiptStatus) + Deposit status (DepositStatus) + Ref. account No. (Udfield1) - Update deposit account for collect fee | G112: + | I112: 45631 | O112: VyHNT
A113: ='Scenario Test'!$A$15 -> DPT_CER | B113: =VLOOKUP(TestCase!A113,'Scenario Test'!$A$4:$B$125,2,0) -> DPT_CER: 11803: Fixed deposit receipt issue | C113: DPT_CER_007 | E113: Account number is empty | F113: Transaction failed Show error message | G113: + | I113: 45631 | O113: VyHNT
A114: ='Scenario Test'!$A$15 -> DPT_CER | B114: =VLOOKUP(TestCase!A114,'Scenario Test'!$A$4:$B$125,2,0) -> DPT_CER: 11803: Fixed deposit receipt issue | C114: DPT_CER_008 | E114: Account number does not exist | F114: Transaction failed Show error message | G114: + | I114: 45631 | O114: VyHNT
A115: ='Scenario Test'!$A$15 -> DPT_CER | B115: =VLOOKUP(TestCase!A115,'Scenario Test'!$A$4:$B$125,2,0) -> DPT_CER: 11803: Fixed deposit receipt issue | C115: DPT_CER_009 | E115: Cerfiticate serial is empty | F115: Transaction failed Show error message | G115: + | I115: 45631 | O115: VyHNT
A116: ='Scenario Test'!$A$15 -> DPT_CER | B116: =VLOOKUP(TestCase!A116,'Scenario Test'!$A$4:$B$125,2,0) -> DPT_CER: 11803: Fixed deposit receipt issue | C116: DPT_CER_010 | E116: Cerfiticate serial does not exist | F116: Transaction failed Show error message | G116: + | I116: 45631 | O116: VyHNT
A117: ='Scenario Test'!$A$15 -> DPT_CER | B117: =VLOOKUP(TestCase!A117,'Scenario Test'!$A$4:$B$125,2,0) -> DPT_CER: 11803: Fixed deposit receipt issue | C117: DPT_CER_011 | E117: Books exist - Stock type: <> Receipt - Book status: Assigned to teller - Confirm status: Confirmed - Status of stock leaves: Normal - Belongs to teller does this transaction Deposit account - Deposit type: Fixed deposit - Deposit sub type: Prepaid fixed depsoit account - Deposit status: New/ Normal/ Dormant/ Maturity - Have no receipt | F117: Transaction failed Show error message | G117: + | I117: 45631 | O117: VyHNT
A118: ='Scenario Test'!$A$15 -> DPT_CER | B118: =VLOOKUP(TestCase!A118,'Scenario Test'!$A$4:$B$125,2,0) -> DPT_CER: 11803: Fixed deposit receipt issue | C118: DPT_CER_012 | E118: Books exist - Stock type: Receipt - Book status <> Assigned to teller - Confirm status: Confirmed - Status of stock leaves: Normal - Belongs to teller does this transaction Deposit account - Deposit type: Fixed deposit - Deposit sub type: Prepaid fixed depsoit account - Deposit status: New/ Normal/ Dormant/ Maturity - Have no receipt | F118: Transaction failed Show error message | G118: + | I118: 45631 | O118: VyHNT
... A120: ='Scenario Test'!$A$15 -> DPT_CER | B120: =VLOOKUP(TestCase!A120,'Scenario Test'!$A$4:$B$125,2,0) -> DPT_CER: 11803: Fixed deposit receipt issue | C120: DPT_CER_014 | E120: Books exist - Stock type: Receipt - Book status: Assigned to teller - Confirm status: Confirmed - Status of stock leaves <> Normal - Belongs to teller does this transaction Deposit account - Deposit type: Fixed deposit - Deposit sub type: Prepaid fixed depsoit account - Deposit status: New/ Normal/ Dormant/ Maturity - Have no receipt | F120: Transaction failed Show error message | G120: + | I120: 45631 | O120: VyHNT
A121: ='Scenario Test'!$A$15 -> DPT_CER | B121: =VLOOKUP(TestCase!A121,'Scenario Test'!$A$4:$B$125,2,0) -> DPT_CER: 11803: Fixed deposit receipt issue | C121: DPT_CER_015 | E121: Books exist - Stock type: Receipt - Book status: Assigned to teller - Confirm status: Confirmed - Status of stock leaves: Normal - NOT belong to teller does this transaction Deposit account - Deposit type: Fixed deposit - Deposit sub type: Prepaid fixed depsoit account - Deposit status: New/ Normal/ Dormant/ Maturity - Have no receipt | F121: Transaction failed Show error message | G121: + | H121: check theo hiện trạng trên prod đang không validate | I121: 45631 | O121: VyHNT
A122: ='Scenario Test'!$A$15 -> DPT_CER | B122: =VLOOKUP(TestCase!A122,'Scenario Test'!$A$4:$B$125,2,0) -> DPT_CER: 11803: Fixed deposit receipt issue | C122: DPT_CER_016 | E122: Books exist - Stock type: Receipt - Book status: Assigned to teller - Confirm status: Confirmed - Status of stock leaves: Normal - Belongs to teller does this transaction Deposit account - Deposit type <> Fixed deposit - Deposit status: New/ Normal/ Dormant/ Maturity - Have no receipt | F122: Transaction failed Show error message | G122: + | I122: 45631 | O122: VyHNT
A123: ='Scenario Test'!$A$15 -> DPT_CER | B123: =VLOOKUP(TestCase!A123,'Scenario Test'!$A$4:$B$125,2,0) -> DPT_CER: 11803: Fixed deposit receipt issue | C123: DPT_CER_017 | E123: Books exist - Stock type: Receipt - Book status: Assigned to teller - Confirm status: Confirmed - Status of stock leaves: Normal - Belongs to teller does this transaction Deposit account - Deposit type: Fixed deposit - Deposit sub type <> Prepaid fixed depsoit account - Deposit status: New/ Normal/ Dormant/ Maturity - Have no receipt | F123: Transaction failed Show error message | G123: + | I123: 45631 | O123: VyHNT
A124: ='Scenario Test'!$A$15 -> DPT_CER | B124: =VLOOKUP(TestCase!A124,'Scenario Test'!$A$4:$B$125,2,0) -> DPT_CER: 11803: Fixed deposit receipt issue | C124: DPT_CER_018 | E124: Books exist - Stock type: Receipt - Book status: Assigned to teller - Confirm status: Confirmed - Status of stock leaves: Normal - Belongs to teller does this transaction Deposit account - Deposit type: Fixed deposit - Deposit sub type: Prepaid fixed depsoit account - Deposit status <> New/ Normal/ Dormant/ Maturity - Have no receipt | F124: Transaction failed Show error message | G124: + | I124: 45631 | O124: VyHNT
A125: ='Scenario Test'!$A$15 -> DPT_CER | B125: =VLOOKUP(TestCase!A125,'Scenario Test'!$A$4:$B$125,2,0) -> DPT_CER: 11803: Fixed deposit receipt issue | C125: DPT_CER_019 | E125: Books exist - Stock type: Receipt - Book status: Assigned to teller - Confirm status: Confirmed - Status of stock leaves: Normal - Belongs to teller does this transaction Deposit account - Deposit type: Fixed deposit - Deposit sub type: Prepaid fixed depsoit account - Has receipt with status is Normal - Same branch with stock | F125: Transaction failed Show error message | G125: + | I125: 45631 | O125: VyHNT
A126: ='Scenario Test'!$A$15 -> DPT_CER | B126: =VLOOKUP(TestCase!A126,'Scenario Test'!$A$4:$B$125,2,0) -> DPT_CER: 11803: Fixed deposit receipt issue | C126: DPT_CER_020 | E126: Books exist - Stock type: Receipt - Book status: Assigned to teller - Confirm status: Confirmed - Status of stock leaves: Normal - Belongs to teller does this transaction Deposit account - Deposit type: Fixed deposit - Deposit sub type: Prepaid fixed depsoit account - Have no receipt Fee collect method is Cash - User has NO right to do transaction related to cash | F126: Transaction failed Show error message | G126: + | I126: 45631 | O126: VyHNT
A127: ='Scenario Test'!$A$15 -> DPT_CER | B127: =VLOOKUP(TestCase!A127,'Scenario Test'!$A$4:$B$125,2,0) -> DPT_CER: 11803: Fixed deposit receipt issue | C127: DPT_CER_021 | E127: Books exist: - Stock type: Receipt - Book status: Assigned to teller - Confirm status: Confirmed - Status of stock leaves: Normal - Belongs to teller does this transaction Deposit account - Deposit type: Fixed deposit - Deposit sub type: Prepaid fixed depsoit account - Have no receipt Fee collect method is Deposit - Deposit type: Fixed deposit - Deposit status: Normal - Available balance >= Total fee amount - Same currency with account is issued stock | F127: Transaction failed Show error message | G127: + | I127: 45631 | O127: VyHNT
A128: ='Scenario Test'!$A$15 -> DPT_CER | B128: =VLOOKUP(TestCase!A128,'Scenario Test'!$A$4:$B$125,2,0) -> DPT_CER: 11803: Fixed deposit receipt issue | C128: DPT_CER_022 | E128: Books exist - Stock type: Receipt - Book status: Assigned to teller - Confirm status: Confirmed - Status of stock leaves: Normal - Belongs to teller does this transaction Deposit account - Deposit type: Fixed deposit - Deposit sub type: Prepaid fixed depsoit account - Have no receipt Fee collect method is Deposit - Deposit type: Current/ Saving - Deposit status <> Normal - Available balance >= total fee amount - Same currency with account is issued stock | F128: Transaction failed Show error message | G128: + | I128: 45631 | O128: VyHNT
...

Sheet UpdateData
A1: Action | B1: Update data | C1: Update related table
C2: o9accounting | E2: o9admin | G2: o9cash | I2: o9deposit
C3: Table name | D3: Action | E3: Table name | F3: Action | G3: Table name | H3: Action | I3: Table name | J3: Action
A4: Issue stock | B4: Stock inventory - Book status: Normal - Ref. account No.: Deposit issued stock - Stock leaves status = Pslsts: change all leaves to Unpaid (if stock type is Cheque) Deposit account (if stock type is not Cheque) - Passbook or receipt number: Serial no - Udfield1: Execution id of transaction Fee collect method is cash - Increase Customer deposit, Total In, Closing balance of Cash flow Fee collect method is deposit - Decrease Current balance, Available balance - Increase Withdraw Amount, Week Debit, Month Debit, Quarter Debit, Semi - Annual Debit and Year Debit Fee collect method is GL - Decrease GL Balance | C4: GLEntries | D4: Insert new row | E4: TransactionJournalDone | F4: Insert new row | G4: CashList | H4: - CurrencyCode already existed: Update old row (update CurrentBalance) - CurrencyCode does not exist: Insert new row | I4: Stock inventory | J4: Update old row - BookStatus - RefAccountNo - StockLeavesStatus, Pslsts (if stock type is Cheque)
C5: AccountBalance | D5: Update old row (update Balance) | E5: Transaction | F5: Insert new row | G5: CashStatement | H5: - CashierCode, CurrencyCode, CashType and ValueDate already existed: Update old row (update CashAmount) - CashierCode, CurrencyCode, CashType and ValueDate do not exist: Insert new row | I5: DepositAccount | J5: Update old row (if stock type is not Cheque) - PassbookOrReceiptNumber - Udfield1 Update old row (if withdraw by deposit) - DepositStatus (if prevoius status is New) - Psts - CurrentBalance, DepositAmount, WeekCredit, MonthCredit, QuarterCredit, SemiAnnualCredit, YearCredit - LastTransactionDate, UpdatedOnUtc
C6: AccountStatement | D6: Insert new row | E6: TransactionDetail | F6: Insert new row | G6: CashTransaction | H6: Insert new row | I6: DepositHistory | J6: Insert new row
C7: Transaction | D7: Insert new row | G7: GLEntries | H7: Insert new row | I7: Transaction | J7: Insert new row
C8: TransactionDetail | D8: Insert new row | G8: Transaction | H8: Insert new row | I8: TransactionDetail | J8: Insert new row
G9: TransactionDetail | H9: Insert new row
A10: Withdraw money by cheque | B10: Stock inventory - Stock leaves status: Paid 'Deposit account - Decrease Current balance, Available balance - Increase Withdraw Amount, Week Debit, Month Debit, Quarter Debit, Semi - Annual Debit and Year Debit Withdraw by cash - Increase Customer withdrawal, Total Out, decrease Closing balance of Cash flow Withdraw by deposit - Increase Current balance, Available balance - Increase Deposit Amount, Week Credit, Month Credit, Quarter Credit, Semi - Annual Credit and Year Credit Withdraw by GL - Increase GL Balance | C10: GLEntries | D10: Insert new row | E10: TransactionJournalDone | F10: Insert new row | G10: CashList | H10: Update old row (update CurrentBalance) | I10: Stock inventory | J10: Update old row - StockLeavesStatus
C11: AccountStatement | D11: Insert new row | E11: Transaction | F11: Insert new row | G11: CashStatement | H11: - CashierCode, CurrencyCode, CashType and ValueDate already existed: Update old row (update CashAmount) - CashierCode, CurrencyCode, CashType and ValueDate do not exist: Insert new row | I11: DepositAccount | J11: Update old row - DepositStatus (if prevoius status is New) - Psts - CurrentBalance, WithdrawAmount, WeekDebit, MonthDebit, QuarterDebit, SemiAnnualDebit, YearDebit - LastTransactionDate, UpdatedOnUtc - LastChangeDormantToNormalDate (if previous status is Dormant) Update old row (if withdraw by deposit) - DepositStatus (if prevoius status is New) - Psts - CurrentBalance, DepositAmount, WeekCredit, MonthCredit, QuarterCredit, SemiAnnualCredit, YearCredit - LastTransactionDate, UpdatedOnUtc
C12: Transaction | D12: Insert new row | E12: TransactionDetail | F12: Insert new row | G12: CashTransaction | H12: Insert new row | I12: DepositStatement | J12: Insert new row
C13: TransactionDetail | D13: Insert new row | G13: GLEntries | H13: Insert new row | I13: DepositHistory | J13: Insert new row
G14: Transaction | H14: Insert new row | I14: DepositAccountTrans | J14: Insert new row
G15: TransactionDetail | H15: Insert new row | I15: GLEntries | J15: Insert new row
I16: Transaction | J16: Insert new row
I17: TransactionDetail | J17: Insert new row
